Workbook
Name Mongeral_TM_10: "Teste"
Name Produtos: #N/A
Name Teste2: #N/A

Sheet Simulador
A1: Inserir dados | I1: Nascimento
A2: Nome | C2: Idade | E2: Capital Segurado | F2: Sexo | G2: IPCA | H2: Period. | I2: 29159
A3: Augusto Giani | B3: DANIEL | C3: 28 | D3: 64 | E3: 150000 | F3: Masculino | G3: 0.055 | H3: Mensal | I3: =TODAY() -> 46127
I4: =INT((I3-I2))/365.25 -> 46.455852
A5: ESTRATÉGIA DE MÉDIO PRAZO
A6: SEGURO RESGATÁVEL | Dinâmica Financeira | F6: =A3 -> Augusto Giani
A7: PROTEÇÃO FAMILIAR + FORMAÇÃO DE RESERVA | J7: Aporte c/ Agravo
A8: =TODAY() -> 46127
A9: * Considerando IPCA de | C9: =G3 -> 0.055 | D9: aa | E9: aa
A10: O valor de resgate apresentado considera que os prêmios (aportes) são pagos em dia e já está capitalizado atuarialmente com base na taxa de juros de 3% ao ano, restando apenas aplicar o índice de atualização monetária referente ao IPCA mensalmente. A capitalização atuarial utilizada nestes cálculos considera fatores tais como probabilidade de morte, idade, sexo, ano de vigência da apólice e capital segurado.
A11: Congelamento de Risco: | C11: =C3 -> 28 | D11: anos | E11: anos
A13: Anos | B13: Capital Segurado | D13: =IF(H3="Anual","Aporte Anual","Aporte Mensal") -> Aporte Mensal | E13: Aporte Anual | F13: Aporte Acumulado | G13: Reserva Acumulada | J13: Morte Acidental | K13: Aporte
A14: =C3+1 -> 29 | B14: =IFERROR(IF(A14="","",$E$3),"") -> 150000 | D14: =IF(H3="Anual",IF(J8=0,IF(F3="Masculino",Simulações!E7,Simulações!G7),J8),IF(J8=0,IF(F3="Masculino",Simulações!E9,Simulações!G9),J8)) -> 469.82357 | E14: =D14*12*0.97352 -> 5488.5917 | F14: =E14 -> 5488.5917 | G14: =IFERROR(IF($F$3="Masculino",B14*(HLOOKUP($C$3,Resgate!$E$1:$BD$87,Resgate!D2,FALSE)),B14*(HLOOKUP($C$3,Resgate!$BF$1:$DE$87,Resgate!D2,FALSE))),"") -> 0 | H14: =G14/F14 -> 0 | J14: 0 | L14: =IF(J14=0,"",IF(OR(J14>1000000,J14<160000,),"CS ñ Permitido",IF(J14>E3,"CS ñ Permitido",IF(H3="Anual",Simulações!K10,Simulações!K12))))
A15: =IF(A14="","",IF(A14+1>100,"",A14+1)) -> 30 | B15: =IFERROR(IF(A15="","",B14)*(1+$G$3),"") -> 158250 | D15: =D14*(1+$G$3) -> 495.66387 | E15: =D15*12*0.97352 -> 5790.4643 | F15: =F14+E15 -> 11279.056 | G15: =IFERROR(IF($F$3="Masculino",B15*(HLOOKUP($C$3,Resgate!$E$1:$BD$87,Resgate!D3,FALSE)),B15*(HLOOKUP($C$3,Resgate!$BF$1:$DE$87,Resgate!D3,FALSE))),"") -> 0 | H15: =G15/F15 -> 0 | J15: Invalidez Acidental
A16: =IF(A15="","",IF(A15+1>100,"",A15+1)) -> 31 | B16: =IFERROR(IF(A16="","",B15)*(1+$G$3),"") -> 166953.75 | D16: =D15*(1+$G$3) -> 522.92538 | E16: =D16*12*0.97352 -> 6108.9398 | F16: =F15+E16 -> 17387.996 | G16: =IFERROR(IF($F$3="Masculino",B16*(HLOOKUP($C$3,Resgate!$E$1:$BD$87,Resgate!D4,FALSE)),B16*(HLOOKUP($C$3,Resgate!$BF$1:$DE$87,Resgate!D4,FALSE))),"") -> 2500.9672 | H16: =G16/F16 -> 0.14383298 | J16: 200000 | K16: =(L16*12)*0.97352 -> #VALUE! | L16: =IF(J16=0,"",IF(OR(J16>1000000,J16<160000,),"CS ñ Permitido",IF(J16>E3,"CS ñ Permitido",IF(H3="Anual",Simulações!Y10,Simulações!Y12)))) -> CS ñ Permitido
A17: =IF(A16="","",IF(A16+1>100,"",A16+1)) -> 32 | B17: =IFERROR(IF(A17="","",B16)*(1+$G$3),"") -> 176136.21 | D17: =D16*(1+$G$3) -> 551.68628 | E17: =D17*12*0.97352 -> 6444.9315 | F17: =F16+E17 -> 23832.927 | G17: =IFERROR(IF($F$3="Masculino",B17*(HLOOKUP($C$3,Resgate!$E$1:$BD$87,Resgate!D5,FALSE)),B17*(HLOOKUP($C$3,Resgate!$BF$1:$DE$87,Resgate!D5,FALSE))),"") -> 6668.5168 | H17: =G17/F17 -> 0.27980267 | J17: Doenças Graves Plus
A18: =IF(A17="","",IF(A17+1>100,"",A17+1)) -> 33 | B18: =IFERROR(IF(A18="","",B17)*(1+$G$3),"") -> 185823.7 | D18: =D17*(1+$G$3) -> 582.02902 | E18: =D18*12*0.97352 -> 6799.4027 | F18: =F17+E18 -> 30632.33 | G18: =IFERROR(IF($F$3="Masculino",B18*(HLOOKUP($C$3,Resgate!$E$1:$BD$87,Resgate!D6,FALSE)),B18*(HLOOKUP($C$3,Resgate!$BF$1:$DE$87,Resgate!D6,FALSE))),"") -> 14353.022 | H18: =G18/F18 -> 0.46855797 | J18: 200000 | K18: =(L18*12)*0.97352 -> #VALUE! | L18: =IF(J18=0,"",IF(OR(J18>1000000,J18<160000),"CS ñ Permitido",IF(H3="Anual",IF(J8=0,IF(F3="Masculino",Simulações!AB7,Simulações!AD7),J8),IF(J8=0,IF(F3="Masculino",Simulações!AB9,Simulações!AD9),J8)))) -> #VALUE!
A19: =IF(A18="","",IF(A18+1>100,"",A18+1)) -> 34 | B19: =IFERROR(IF(A19="","",B18)*(1+$G$3),"") -> 196044 | D19: =D18*(1+$G$3) -> 614.04062 | E19: =D19*12*0.97352 -> 7173.3699 | F19: =F18+E19 -> 37805.7 | G19: =IFERROR(IF($F$3="Masculino",B19*(HLOOKUP($C$3,Resgate!$E$1:$BD$87,Resgate!D7,FALSE)),B19*(HLOOKUP($C$3,Resgate!$BF$1:$DE$87,Resgate!D7,FALSE))),"") -> 22554.862 | H19: =G19/F19 -> 0.59659952 | J19: Renda Hospitalar
A20: =IF(A19="","",IF(A19+1>100,"",A19+1)) -> 35 | B20: =IFERROR(IF(A20="","",B19)*(1+$G$3),"") -> 206826.42 | D20: =D19*(1+$G$3) -> 647.81285 | E20: =D20*12*0.97352 -> 7567.9052 | F20: =F19+E20 -> 45373.605 | G20: =IFERROR(IF($F$3="Masculino",B20*(HLOOKUP($C$3,Resgate!$E$1:$BD$87,Resgate!D8,FALSE)),B20*(HLOOKUP($C$3,Resgate!$BF$1:$DE$87,Resgate!D8,FALSE))),"") -> 33317.668 | H20: =G20/F20 -> 0.73429625 | J20: 1000 | K20: =(L20*12)*0.97352 -> 591.02228 | L20: =IF(J20=0,"",IF(J20<300,"Mínimo 300,00",IF(H3="Anual",Simulações!U7,Simulações!U9))) -> 50.59152
A21: =IF(A20="","",IF(A20+1>100,"",A20+1)) -> 36 | B21: =IFERROR(IF(A21="","",B20)*(1+$G$3),"") -> 218201.87 | D21: =D20*(1+$G$3) -> 683.44256 | E21: =D21*12*0.97352 -> 7984.14 | F21: =F20+E21 -> 53357.745 | G21: =IFERROR(IF($F$3="Masculino",B21*(HLOOKUP($C$3,Resgate!$E$1:$BD$87,Resgate!D9,FALSE)),B21*(HLOOKUP($C$3,Resgate!$BF$1:$DE$87,Resgate!D9,FALSE))),"") -> 47072.69 | H21: =G21/F21 -> 0.88220914 | J21: Total | K21: =K20+K18+K16+K14 -> #VALUE! | L21: =SUM(L14,L16,L20,L18) -> #VALUE!
A22: =IF(A21="","",IF(A21+1>100,"",A21+1)) -> 37 | B22: =IFERROR(IF(A22="","",B21)*(1+$G$3),"") -> 230202.98 | D22: =D21*(1+$G$3) -> 721.0319 | E22: =D22*12*0.97352 -> 8423.2677 | F22: =F21+E22 -> 61781.013 | G22: =IFERROR(IF($F$3="Masculino",B22*(HLOOKUP($C$3,Resgate!$E$1:$BD$87,Resgate!D10,FALSE)),B22*(HLOOKUP($C$3,Resgate!$BF$1:$DE$87,Resgate!D10,FALSE))),"") -> 64304.9 | H22: =G22/F22 -> 1.0408521
A23: =IF(A22="","",IF(A22+1>100,"",A22+1)) -> 38 | B23: =IFERROR(IF(A23="","",B22)*(1+$G$3),"") -> 242864.14 | D23: =D22*(1+$G$3) -> 760.68865 | E23: =D23*12*0.97352 -> 8886.5474 | F23: =F22+E23 -> 70667.56 | G23: =IFERROR(IF($F$3="Masculino",B23*(HLOOKUP($C$3,Resgate!$E$1:$BD$87,Resgate!D11,FALSE)),B23*(HLOOKUP($C$3,Resgate!$BF$1:$DE$87,Resgate!D11,FALSE))),"") -> 90066.167 | H23: =G23/$F$23 -> 1.2745051 | J23: =IF(H3="Anual","Total Anual","Total Mensal") -> Total Mensal | K23: =K21+E14 -> #VALUE! | L23: =L21+D14 -> #VALUE!
A24: =IF(A23="","",IF(A23+1>100,"",A23+1)) -> 39 | B24: =IFERROR(IF(A24="","",B23)*(1+$G$3),"") -> 256221.67 | E24: Apólice Quitada | G24: =IFERROR(IF($F$3="Masculino",B24*(HLOOKUP($C$3,Resgate!$E$1:$BD$87,Resgate!D12,FALSE)),B24*(HLOOKUP($C$3,Resgate!$BF$1:$DE$87,Resgate!D12,FALSE))),"") -> 97443.663 | H24: =G24/$F$23 -> 1.3789023 | J24: *Tributação de acordo com a legislação vigente
A25: =IF(A24="","",IF(A24+1>100,"",A24+1)) -> 40 | B25: =IFERROR(IF(A25="","",B24)*(1+$G$3),"") -> 270313.86 | G25: =IFERROR(IF($F$3="Masculino",B25*(HLOOKUP($C$3,Resgate!$E$1:$BD$87,Resgate!D13,FALSE)),B25*(HLOOKUP($C$3,Resgate!$BF$1:$DE$87,Resgate!D13,FALSE))),"") -> 105408.89 | H25: =G25/$F$23 -> 1.4916164
A26: =IF(A25="","",IF(A25+1>100,"",A25+1)) -> 41 | B26: =IFERROR(IF(A26="","",B25)*(1+$G$3),"") -> 285181.12 | G26: =IFERROR(IF($F$3="Masculino",B26*(HLOOKUP($C$3,Resgate!$E$1:$BD$87,Resgate!D14,FALSE)),B26*(HLOOKUP($C$3,Resgate!$BF$1:$DE$87,Resgate!D14,FALSE))),"") -> 114004.01 | H26: =G26/$F$23 -> 1.6132438
A27: =IF(A26="","",IF(A26+1>100,"",A26+1)) -> 42 | B27: =IFERROR(IF(A27="","",B26)*(1+$G$3),"") -> 300866.08 | G27: =IFERROR(IF($F$3="Masculino",B27*(HLOOKUP($C$3,Resgate!$E$1:$BD$87,Resgate!D15,FALSE)),B27*(HLOOKUP($C$3,Resgate!$BF$1:$DE$87,Resgate!D15,FALSE))),"") -> 123276.87 | H27: =G27/$F$23 -> 1.7444619
A28: =IF(A27="","",IF(A27+1>100,"",A27+1)) -> 43 | B28: =IFERROR(IF(A28="","",B27)*(1+$G$3),"") -> 317413.72 | G28: =IFERROR(IF($F$3="Masculino",B28*(HLOOKUP($C$3,Resgate!$E$1:$BD$87,Resgate!D16,FALSE)),B28*(HLOOKUP($C$3,Resgate!$BF$1:$DE$87,Resgate!D16,FALSE))),"") -> 133275.67 | H28: =G28/$F$23 -> 1.8859527
A29: =IF(A28="","",IF(A28+1>100,"",A28+1)) -> 44 | B29: =IFERROR(IF(A29="","",B28)*(1+$G$3),"") -> 334871.47 | G29: =IFERROR(IF($F$3="Masculino",B29*(HLOOKUP($C$3,Resgate!$E$1:$BD$87,Resgate!D17,FALSE)),B29*(HLOOKUP($C$3,Resgate!$BF$1:$DE$87,Resgate!D17,FALSE))),"") -> 144055.01 | H29: =G29/$F$23 -> 2.0384885
A30: =IF(A29="","",IF(A29+1>100,"",A29+1)) -> 45 | B30: =IFERROR(IF(A30="","",B29)*(1+$G$3),"") -> 353289.4 | G30: =IFERROR(IF($F$3="Masculino",B30*(HLOOKUP($C$3,Resgate!$E$1:$BD$87,Resgate!D18,FALSE)),B30*(HLOOKUP($C$3,Resgate!$BF$1:$DE$87,Resgate!D18,FALSE))),"") -> 155673.44 | H30: =G30/$F$23 -> 2.2028982
A31: =IF(A30="","",IF(A30+1>100,"",A30+1)) -> 46 | B31: =IFERROR(IF(A31="","",B30)*(1+$G$3),"") -> 372720.32 | G31: =IFERROR(IF($F$3="Masculino",B31*(HLOOKUP($C$3,Resgate!$E$1:$BD$87,Resgate!D19,FALSE)),B31*(HLOOKUP($C$3,Resgate!$BF$1:$DE$87,Resgate!D19,FALSE))),"") -> 168193.77 | H31: =G31/$F$23 -> 2.3800705
A32: =IF(A31="","",IF(A31+1>100,"",A31+1)) -> 47 | B32: =IFERROR(IF(A32="","",B31)*(1+$G$3),"") -> 393219.94 | G32: =IFERROR(IF($F$3="Masculino",B32*(HLOOKUP($C$3,Resgate!$E$1:$BD$87,Resgate!D20,FALSE)),B32*(HLOOKUP($C$3,Resgate!$BF$1:$DE$87,Resgate!D20,FALSE))),"") -> 181683.34 | H32: =G32/$F$23 -> 2.5709582
A33: =IF(A32="","",IF(A32+1>100,"",A32+1)) -> 48 | B33: =IFERROR(IF(A33="","",B32)*(1+$G$3),"") -> 414847.04 | G33: =IFERROR(IF($F$3="Masculino",B33*(HLOOKUP($C$3,Resgate!$E$1:$BD$87,Resgate!D21,FALSE)),B33*(HLOOKUP($C$3,Resgate!$BF$1:$DE$87,Resgate!D21,FALSE))),"") -> 196218.5 | H33: =G33/$F$23 -> 2.7766418
A34: =IF(A33="","",IF(A33+1>100,"",A33+1)) -> 49 | B34: =IFERROR(IF(A34="","",B33)*(1+$G$3),"") -> 437663.62 | G34: =IFERROR(IF($F$3="Masculino",B34*(HLOOKUP($C$3,Resgate!$E$1:$BD$87,Resgate!D22,FALSE)),B34*(HLOOKUP($C$3,Resgate!$BF$1:$DE$87,Resgate!D22,FALSE))),"") -> 211872.96 | H34: =G34/$F$23 -> 2.9981644
A35: =IF(A34="","",IF(A34+1>100,"",A34+1)) -> 50 | B35: =IFERROR(IF(A35="","",B34)*(1+$G$3),"") -> 461735.12 | G35: =IFERROR(IF($F$3="Masculino",B35*(HLOOKUP($C$3,Resgate!$E$1:$BD$87,Resgate!D23,FALSE)),B35*(HLOOKUP($C$3,Resgate!$BF$1:$DE$87,Resgate!D23,FALSE))),"") -> 228725.11 | H35: =G35/$F$23 -> 3.2366352
A36: =IF(A35="","",IF(A35+1>100,"",A35+1)) -> 51 | B36: =IFERROR(IF(A36="","",B35)*(1+$G$3),"") -> 487130.55 | G36: =IFERROR(IF($F$3="Masculino",B36*(HLOOKUP($C$3,Resgate!$E$1:$BD$87,Resgate!D24,FALSE)),B36*(HLOOKUP($C$3,Resgate!$BF$1:$DE$87,Resgate!D24,FALSE))),"") -> 246863.15 | H36: =G36/$F$23 -> 3.4933023
... A99: =IF(A98="","",IF(A98+1>100,"",A98+1)) | B99: =IFERROR(IF(A99="","",B98)*(1+$G$3),"") | G99: =IFERROR(IF($F$3="Masculino",B99*(HLOOKUP($C$3,Resgate!$E$1:$BD$87,Resgate!D87,FALSE)),B99*(HLOOKUP($C$3,Resgate!$BF$1:$DE$87,Resgate!D87,FALSE))),"") | H99: =G99/$F$23 -> #VALUE!

Sheet Valores IOF
B3: Periodicidade Anual | C3: Prêmio Líquido | D3: IOF | E3: Prêmio Bruto
B4: Vida Inteira | C4: =IF(Simulador!F3="Masculino",SUM(Simulações!F3:F54),SUM(Simulações!H3:H54)) -> 5200.5 | D4: =C4*0.38% -> 19.7619 | E4: =C4+D4 -> 5220.2619
B5: Morte Acidental | C5: =Simulador!J14*Simulações!K3/1000 -> 0 | D5: =C5*0.38% -> 0 | E5: =C5+D5 -> 0
B6: Invalidez Acidental | C6: =Simulador!J16*Simulações!Y3/1000 -> 100 | D6: =C6*0.38% -> 0.38 | E6: =C6+D6 -> 100.38
B7: Doenças Graves Plus | C7: =IF(Simulador!F3="Masculino",SUM(Simulações!AC3:AC54),SUM(Simulações!AE3:AE54)) -> 264 | D7: =C7*0.38% -> 1.0032 | E7: =C7+D7 -> 265.0032
B8: Renda Hospitalar | C8: =IF(Simulador!F3="Masculino",SUM(Simulações!T3:T54),SUM(Simulações!V3:V54)) -> 560 | D8: =C8*0.38% -> 2.128 | E8: =C8+D8 -> 562.128
B9: Total | C9: =SUM(C4:C8) -> 6124.5 | D9: =SUM(D4:D8) -> 23.2731 | E9: =SUM(E4:E8) -> 6147.7731
C10: ]
B12: Periodicidade Mensal | C12: Prêmio Líquido | D12: IOF | E12: Prêmio Bruto
B13: Vida Inteira | C13: 950 | D13: =C13*0.38% -> 3.61 | E13: =C13+D13 -> 953.61
B14: Morte Acidental | C14: =C5*0.09 -> 0 | D14: =C14*0.38% -> 0 | E14: =C14+D14 -> 0
B15: Invalidez Acidental | C15: 10 | D15: =C15*0.38% -> 0.038 | E15: =C15+D15 -> 10.038
B16: Doenças Graves Plus | C16: =C7*0.09 -> 23.76 | D16: =C16*0.38% -> 0.090288 | E16: =C16+D16 -> 23.850288
B17: Renda Hospitalar | C17: =C8*0.09 -> 50.4 | D17: =C17*0.38% -> 0.19152 | E17: =C17+D17 -> 50.59152 | F17: Prêmio Anual Total Fracionado
B18: Total | C18: =SUM(C13:C17) -> 1034.16 | D18: =SUM(D13:D17) -> 3.929808 | E18: =SUM(E13:E17) -> 1038.0898 | F18: =E18*12 -> 12457.078

Sheet Simulações
A1: Idade | B1: WL10 X | C1: WL10 X | D1: Masculino | E1: WL10 Masculino | G1: WL 10 Feminino | J1: Idade | K1: Morte Acidental | O1: Idade | P1: Renda Hospitalar | X1: Idade | Y1: Invalidez Parcial | AF1: Idade | AG1: DDR - Plus | AL1: Idade | AM1: DDR - Básico | AR1: Idade | AS1: WL20 C | AU1: Masculino | AV1: WL20 Masculino | AX1: WL 20 Feminino
B2: Masc | C2: Fem | D2: Feminino | E2: Idade | G2: Idade | K2: Masc | L2: Fem | P2: Masc | Q2: Fem | S2: Masculino | U2: Feminino | Y2: Masc | Z2: Fem | AB2: Masculinio | AD2: Feminino | AG2: Mas | AH2: Fem | AM2: Mas | AN2: Fem | AS2: Masc | AT2: Fem | AU2: Feminino | AV2: Idade | AX2: Idade
A3: 14 | B3: 24.4 | C3: 21.27 | E3: =Simulador!C3 -> 28 | F3: =IF($E$3=A3,$E$5*B3,"") | G3: =Simulador!C3 -> 28 | H3: =IF($G$3=A3,$G$5*C3,"") | J3: 14 | K3: 1.08 | L3: 1.08 | O3: 14 | P3: 0.56 | Q3: 0.56 | R3: =P3-Q3 -> 0 | S3: =Simulador!C3 -> 28 | T3: =IF($S$3=O3,$S$5*P3,"") | U3: =Simulador!C3 -> 28 | V3: =IF($U$3=O3,$U$5*Q3,"") | X3: 14 | Y3: 0.5 | Z3: 0.5 | AB3: =Simulador!C3 -> 28 | AC3: =IF($AB$3=AF3,$AB$5*AG3,"") | AD3: =Simulador!C3 -> 28 | AE3: =IF($AD$3=AF3,$AD$5*AH3,"") | AF3: 14 | AG3: 0.62 | AH3: 0.61 | AL3: 14 | AM3: 0.48 | AN3: 0.49 | AR3: 14 | AS3: 18.05 | AT3: 15.95 | AV3: =Simulador!C3 -> 28 | AW3: =IF($AV$3=AR3,$AV$5*AS3,"") | AX3: =Simulador!C3 -> 28 | AY3: =IF($AX$3=AR3,$AX$5*AT3,"")
A4: 15 | B4: 25.03 | C4: 21.83 | E4: Capital Segurado | F4: =IF($E$3=A4,$E$5*B4,"") | G4: Capital Segurado | H4: =IF($G$3=A4,$G$5*C4,"") | O4: =O3+1 -> 15 | P4: 0.56 | Q4: 0.56 | R4: =P4-Q4 -> 0 | S4: Capital Segurado | T4: =IF($S$3=O4,$S$5*P4,"") | U4: Capital Segurado | V4: =IF($U$3=O4,$U$5*Q4,"") | AB4: Capital Segurado | AC4: =IF($AB$3=AF4,$AB$5*AG4,"") | AD4: Capital Segurado | AE4: =IF($AD$3=AF4,$AD$5*AH4,"") | AF4: =AF3+1 -> 15 | AG4: 0.62 | AH4: 0.61 | AL4: =AL3+1 -> 15 | AM4: 0.48 | AN4: 0.49 | AR4: 15 | AS4: 18.51 | AT4: 16.37 | AV4: Capital Segurado | AW4: =IF($AV$3=AR4,$AV$5*AS4,"") | AX4: Capital Segurado | AY4: =IF($AX$3=AR4,$AX$5*AT4,"")
A5: 16 | B5: 25.66 | C5: 22.4 | E5: =Simulador!E3/1000 -> 150 | F5: =IF($E$3=A5,$E$5*B5,"") | G5: =Simulador!E3/1000 -> 150 | H5: =IF($G$3=A5,$G$5*C5,"") | K5: Idade | O5: =O4+1 -> 16 | P5: 0.56 | Q5: 0.56 | R5: =P5-Q5 -> 0 | S5: =Simulador!J20 -> 1000 | T5: =IF($S$3=O5,$S$5*P5,"") | U5: =Simulador!J20 -> 1000 | V5: =IF($U$3=O5,$U$5*Q5,"") | Y5: Idade | AB5: =Simulador!J18/1000 -> 200 | AC5: =IF($AB$3=AF5,$AB$5*AG5,"") | AD5: =Simulador!J18/1000 -> 200 | AE5: =IF($AD$3=AF5,$AD$5*AH5,"") | AF5: =AF4+1 -> 16 | AG5: 0.62 | AH5: 0.61 | AL5: =AL4+1 -> 16 | AM5: 0.48 | AN5: 0.49 | AR5: 16 | AS5: 18.97 | AT5: 16.8 | AV5: =Simulador!E3/1000 -> 150 | AW5: =IF($AV$3=AR5,$AV$5*AS5,"") | AX5: =Simulador!E3/1000 -> 150 | AY5: =IF($AX$3=AR5,$AX$5*AT5,"")
A6: 17 | B6: 26.28 | C6: 22.99 | E6: Prêmio Anual | F6: =IF($E$3=A6,$E$5*B6,"") | G6: Prêmio Anual | H6: =IF($G$3=A6,$G$5*C6,"") | K6: =G3 -> 28 | O6: =O5+1 -> 17 | P6: 0.56 | Q6: 0.56 | R6: =P6-Q6 -> 0 | S6: Prêmio Anual | T6: =IF($S$3=O6,$S$5*P6,"") | U6: Prêmio Anual | V6: =IF($U$3=O6,$U$5*Q6,"") | Y6: =U3 -> 28 | AB6: Prêmio Anual | AC6: =IF($AB$3=AF6,$AB$5*AG6,"") | AD6: Prêmio Anual | AE6: =IF($AD$3=AF6,$AD$5*AH6,"") | AF6: =AF5+1 -> 17 | AG6: 0.63 | AH6: 0.62 | AL6: =AL5+1 -> 17 | AM6: 0.48 | AN6: 0.5 | AR6: 17 | AS6: 19.44 | AT6: 17.24 | AV6: Prêmio Anual | AW6: =IF($AV$3=AR6,$AV$5*AS6,"") | AX6: Prêmio Anual | AY6: =IF($AX$3=AR6,$AX$5*AT6,"")
A7: 18 | B7: 26.91 | C7: 23.59 | E7: =(IF(F3:F54<=0,"",SUM(F3:F54))*0.38%+(IF(F3:F54<=0,"",SUM(F3:F54)))) -> 5220.2619 | F7: =IF($E$3=A7,$E$5*B7,"") | G7: =IF(H3:H54<=0,"",SUM(H3:H54))*0.38%+(IF(H3:H54<=0,"",SUM(H3:H54))) -> 4700.7954 | H7: =IF($G$3=A7,$G$5*C7,"") | K7: Capital Segurado | O7: =O6+1 -> 18 | P7: 0.56 | Q7: 0.56 | R7: =P7-Q7 -> 0 | S7: =IF(OR(S5<300,S5>1500,),"Máximo 1.500,00",(IF(T3:T54<=0,"",SUM(T3:T54)))*0.38%+(IF(T3:T54<=0,"",SUM(T3:T54)))) -> 562.128 | T7: =IF($S$3=O7,$S$5*P7,"") | U7: =IF(OR(U5<300,U5>1500,),"Máximo 1.500,00",(IF(V3:V54<=0,"",SUM(V3:V54)))*0.38%+(IF(V3:V54<=0,"",SUM(V3:V54)))) -> 562.128 | V7: =IF($U$3=O7,$U$5*Q7,"") | Y7: Capital Segurado | AB7: =IF(E5<160,"Capital Mínimo R$ 160k",(IF(AC3:AC54<=0,"",SUM(AC3:AC54)))*0.38%+(IF(AC3:AC54<=0,"",SUM(AC3:AC54)))) -> Capital Mínimo R$ 160k | AC7: =IF($AB$3=AF7,$AB$5*AG7,"") | AD7: =IF(G5<160,"Capital Mínimo R$ 160k",(IF(AE3:AE54<=0,"",SUM(AE3:AE54)))*0.38%+(IF(AE3:AE54<=0,"",SUM(AE3:AE54)))) -> Capital Mínimo R$ 160k | AE7: =IF($AD$3=AF7,$AD$5*AH7,"") | AF7: =AF6+1 -> 18 | AG7: 0.66 | AH7: 0.64 | AL7: =AL6+1 -> 18 | AM7: 0.5 | AN7: 0.52 | AR7: 18 | AS7: 19.9 | AT7: 17.7 | AV7: =IF(AV5<160,"Capital Mínimo R$ 160k",(IF(AW3:AW54<=0,"",SUM(AW3:AW54)))*0.38%+(IF(AW3:AW54<=0,"",SUM(AW3:AW54)))) -> Capital Mínimo R$ 160k | AW7: =IF($AV$3=AR7,$AV$5*AS7,"") | AX7: =IF(AX5<160,"Capital Mínimo R$ 160k",(IF(AY3:AY54<=0,"",SUM(AY3:AY54)))*0.38%+(IF(AY3:AY54<=0,"",SUM(AY3:AY54)))) -> Capital Mínimo R$ 160k | AY7: =IF($AX$3=AR7,$AX$5*AT7,"")
A8: 19 | B8: 27.55 | C8: 24.2 | E8: Prêmio Mensal | F8: =IF($E$3=A8,$E$5*B8,"") | G8: Prêmio Mensal | H8: =IF($G$3=A8,$G$5*C8,"") | K8: =Simulador!J14 -> 0 | O8: =O7+1 -> 19 | P8: 0.56 | Q8: 0.56 | R8: =P8-Q8 -> 0 | S8: Prêmio Mensal | T8: =IF($S$3=O8,$S$5*P8,"") | U8: Prêmio Mensal | V8: =IF($U$3=O8,$U$5*Q8,"") | Y8: =Simulador!J16 -> 200000 | AB8: Prêmio Mensal | AC8: =IF($AB$3=AF8,$AB$5*AG8,"") | AD8: Prêmio Mensal | AE8: =IF($AD$3=AF8,$AD$5*AH8,"") | AF8: =AF7+1 -> 19 | AG8: 0.69 | AH8: 0.67 | AL8: =AL7+1 -> 19 | AM8: 0.53 | AN8: 0.54 | AR8: 19 | AS8: 20.38 | AT8: 18.16 | AV8: Prêmio Mensal | AW8: =IF($AV$3=AR8,$AV$5*AS8,"") | AX8: Prêmio Mensal | AY8: =IF($AX$3=AR8,$AX$5*AT8,"")
A9: 20 | B9: 28.21 | C9: 24.83 | E9: =E7*0.09 -> 469.82357 | F9: =IF($E$3=A9,$E$5*B9,"") | G9: =G7*0.09 -> 423.07159 | H9: =IF($G$3=A9,$G$5*C9,"") | K9: Prêmio Anual | O9: =O8+1 -> 20 | P9: 0.56 | Q9: 0.56 | R9: =P9-Q9 -> 0 | S9: =S7*0.09 -> 50.59152 | T9: =IF($S$3=O9,$S$5*P9,"") | U9: =U7*0.09 -> 50.59152 | V9: =IF($U$3=O9,$U$5*Q9,"") | Y9: Prêmio Anual | AB9: =AB7*0.09 -> #VALUE! | AC9: =IF($AB$3=AF9,$AB$5*AG9,"") | AD9: =AD7*0.09 -> #VALUE! | AE9: =IF($AD$3=AF9,$AD$5*AH9,"") | AF9: =AF8+1 -> 20 | AG9: 0.73 | AH9: 0.71 | AL9: =AL8+1 -> 20 | AM9: 0.56 | AN9: 0.57 | AR9: 20 | AS9: 20.86 | AT9: 18.64 | AV9: =AV7*0.09 -> #VALUE! | AW9: =IF($AV$3=AR9,$AV$5*AS9,"") | AX9: =AX7*0.09 -> #VALUE! | AY9: =IF($AX$3=AR9,$AX$5*AT9,"")
A10: 21 | B10: 28.88 | C10: 25.48 | F10: =IF($E$3=A10,$E$5*B10,"") | H10: =IF($G$3=A10,$G$5*C10,"") | K10: =(K8/1000*K3)*0.38%+((K8/1000*K3)) -> 0 | O10: =O9+1 -> 21 | P10: 0.56 | Q10: 0.56 | R10: =P10-Q10 -> 0 | T10: =IF($S$3=O10,$S$5*P10,"") | V10: =IF($U$3=O10,$U$5*Q10,"") | Y10: =(Y8/1000*Y3)*0.38%+((Y8/1000*Y3)) -> 100.38 | AC10: =IF($AB$3=AF10,$AB$5*AG10,"") | AE10: =IF($AD$3=AF10,$AD$5*AH10,"") | AF10: =AF9+1 -> 21 | AG10: 0.8 | AH10: 0.77 | AL10: =AL9+1 -> 21 | AM10: 0.6 | AN10: 0.61 | AR10: 21 | AS10: 21.36 | AT10: 19.13 | AW10: =IF($AV$3=AR10,$AV$5*AS10,"") | AY10: =IF($AX$3=AR10,$AX$5*AT10,"")
A11: 22 | B11: 29.57 | C11: 26.15 | F11: =IF($E$3=A11,$E$5*B11,"") | H11: =IF($G$3=A11,$G$5*C11,"") | I11: =IF(G4="Anual",IF(H4=0,IF(E4="Masculino",Simulações!AB7,Simulações!AD7),H4),IF(H4=0,IF(E4="Masculino",Simulações!E9,Simulações!G9),H4)) | K11: Prêmio Mensal | O11: =O10+1 -> 22 | P11: 0.56 | Q11: 0.56 | R11: =P11-Q11 -> 0 | T11: =IF($S$3=O11,$S$5*P11,"") | V11: =IF($U$3=O11,$U$5*Q11,"") | Y11: Prêmio Mensal | AC11: =IF($AB$3=AF11,$AB$5*AG11,"") | AE11: =IF($AD$3=AF11,$AD$5*AH11,"") | AF11: =AF10+1 -> 22 | AG11: 0.86 | AH11: 0.83 | AL11: =AL10+1 -> 22 | AM11: 0.65 | AN11: 0.66 | AR11: 22 | AS11: 21.88 | AT11: 19.63 | AW11: =IF($AV$3=AR11,$AV$5*AS11,"") | AY11: =IF($AX$3=AR11,$AX$5*AT11,"")
A12: 23 | B12: 30.29 | C12: 26.83 | F12: =IF($E$3=A12,$E$5*B12,"") | H12: =IF($G$3=A12,$G$5*C12,"") | K12: =K10*0.09 -> 0 | O12: =O11+1 -> 23 | P12: 0.56 | Q12: 0.56 | R12: =P12-Q12 -> 0 | T12: =IF($S$3=O12,$S$5*P12,"") | V12: =IF($U$3=O12,$U$5*Q12,"") | Y12: =Y10*0.09 -> 9.0342 | AC12: =IF($AB$3=AF12,$AB$5*AG12,"") | AE12: =IF($AD$3=AF12,$AD$5*AH12,"") | AF12: =AF11+1 -> 23 | AG12: 0.93 | AH12: 0.89 | AL12: =AL11+1 -> 23 | AM12: 0.7 | AN12: 0.7 | AR12: 23 | AS12: 22.27 | AT12: 20.15 | AW12: =IF($AV$3=AR12,$AV$5*AS12,"") | AY12: =IF($AX$3=AR12,$AX$5*AT12,"")
A13: 24 | B13: 31.03 | C13: 27.54 | F13: =IF($E$3=A13,$E$5*B13,"") | H13: =IF($G$3=A13,$G$5*C13,"") | O13: =O12+1 -> 24 | P13: 0.56 | Q13: 0.56 | R13: =P13-Q13 -> 0 | T13: =IF($S$3=O13,$S$5*P13,"") | V13: =IF($U$3=O13,$U$5*Q13,"") | AC13: =IF($AB$3=AF13,$AB$5*AG13,"") | AE13: =IF($AD$3=AF13,$AD$5*AH13,"") | AF13: =AF12+1 -> 24 | AG13: 1 | AH13: 0.97 | AL13: =AL12+1 -> 24 | AM13: 0.76 | AN13: 0.76 | AR13: 24 | AS13: 22.67 | AT13: 20.69 | AW13: =IF($AV$3=AR13,$AV$5*AS13,"") | AY13: =IF($AX$3=AR13,$AX$5*AT13,"")
A14: 25 | B14: 32.14 | C14: 28.87 | F14: =IF($E$3=A14,$E$5*B14,"") | H14: =IF($G$3=A14,$G$5*C14,"") | O14: =O13+1 -> 25 | P14: 0.56 | Q14: 0.56 | R14: =P14-Q14 -> 0 | T14: =IF($S$3=O14,$S$5*P14,"") | V14: =IF($U$3=O14,$U$5*Q14,"") | AC14: =IF($AB$3=AF14,$AB$5*AG14,"") | AE14: =IF($AD$3=AF14,$AD$5*AH14,"") | AF14: =AF13+1 -> 25 | AG14: 1.08 | AH14: 1.05 | AL14: =AL13+1 -> 25 | AM14: 0.81 | AN14: 0.83 | AR14: 25 | AS14: 22.95 | AT14: 20.96 | AW14: =IF($AV$3=AR14,$AV$5*AS14,"") | AY14: =IF($AX$3=AR14,$AX$5*AT14,"")
A15: 26 | B15: 32.95 | C15: 29.63 | F15: =IF($E$3=A15,$E$5*B15,"") | H15: =IF($G$3=A15,$G$5*C15,"") | O15: =O14+1 -> 26 | P15: 0.56 | Q15: 0.56 | R15: =P15-Q15 -> 0 | T15: =IF($S$3=O15,$S$5*P15,"") | V15: =IF($U$3=O15,$U$5*Q15,"") | AC15: =IF($AB$3=AF15,$AB$5*AG15,"") | AE15: =IF($AD$3=AF15,$AD$5*AH15,"") | AF15: =AF14+1 -> 26 | AG15: 1.16 | AH15: 1.16 | AL15: =AL14+1 -> 26 | AM15: 0.88 | AN15: 0.92 | AR15: 26 | AS15: 23.24 | AT15: 21.23 | AW15: =IF($AV$3=AR15,$AV$5*AS15,"") | AY15: =IF($AX$3=AR15,$AX$5*AT15,"")
A16: 27 | B16: 33.79 | C16: 30.42 | F16: =IF($E$3=A16,$E$5*B16,"") | H16: =IF($G$3=A16,$G$5*C16,"") | O16: =O15+1 -> 27 | P16: 0.56 | Q16: 0.56 | R16: =P16-Q16 -> 0 | T16: =IF($S$3=O16,$S$5*P16,"") | V16: =IF($U$3=O16,$U$5*Q16,"") | AC16: =IF($AB$3=AF16,$AB$5*AG16,"") | AE16: =IF($AD$3=AF16,$AD$5*AH16,"") | AF16: =AF15+1 -> 27 | AG16: 1.24 | AH16: 1.27 | AL16: =AL15+1 -> 27 | AM16: 0.95 | AN16: 1.03 | AR16: 27 | AS16: 23.69 | AT16: 21.52 | AW16: =IF($AV$3=AR16,$AV$5*AS16,"") | AY16: =IF($AX$3=AR16,$AX$5*AT16,"")
A17: 28 | B17: 34.67 | C17: 31.22 | F17: =IF($E$3=A17,$E$5*B17,"") -> 5200.5 | H17: =IF($G$3=A17,$G$5*C17,"") -> 4683 | O17: =O16+1 -> 28 | P17: 0.56 | Q17: 0.56 | R17: =P17-Q17 -> 0 | T17: =IF($S$3=O17,$S$5*P17,"") -> 560 | V17: =IF($U$3=O17,$U$5*Q17,"") -> 560 | AC17: =IF($AB$3=AF17,$AB$5*AG17,"") -> 264 | AE17: =IF($AD$3=AF17,$AD$5*AH17,"") -> 282 | AF17: =AF16+1 -> 28 | AG17: 1.32 | AH17: 1.41 | AL17: =AL16+1 -> 28 | AM17: 1.03 | AN17: 1.16 | AR17: 28 | AS17: 24.17 | AT17: 22.1 | AW17: =IF($AV$3=AR17,$AV$5*AS17,"") -> 3625.5 | AY17: =IF($AX$3=AR17,$AX$5*AT17,"") -> 3315
A18: 29 | B18: 35.57 | C18: 32.05 | F18: =IF($E$3=A18,$E$5*B18,"") | H18: =IF($G$3=A18,$G$5*C18,"") | O18: =O17+1 -> 29 | P18: 0.56 | Q18: 0.56 | R18: =P18-Q18 -> 0 | T18: =IF($S$3=O18,$S$5*P18,"") | V18: =IF($U$3=O18,$U$5*Q18,"") | AC18: =IF($AB$3=AF18,$AB$5*AG18,"") | AE18: =IF($AD$3=AF18,$AD$5*AH18,"") | AF18: =AF17+1 -> 29 | AG18: 1.42 | AH18: 1.57 | AL18: =AL17+1 -> 29 | AM18: 1.11 | AN18: 1.31 | AR18: 29 | AS18: 24.82 | AT18: 22.55 | AW18: =IF($AV$3=AR18,$AV$5*AS18,"") | AY18: =IF($AX$3=AR18,$AX$5*AT18,"")
A19: 30 | B19: 36.5 | C19: 32.9 | F19: =IF($E$3=A19,$E$5*B19,"") | H19: =IF($G$3=A19,$G$5*C19,"") | O19: =O18+1 -> 30 | P19: 0.56 | Q19: 0.56 | R19: =P19-Q19 -> 0 | T19: =IF($S$3=O19,$S$5*P19,"") | V19: =IF($U$3=O19,$U$5*Q19,"") | AC19: =IF($AB$3=AF19,$AB$5*AG19,"") | AE19: =IF($AD$3=AF19,$AD$5*AH19,"") | AF19: =AF18+1 -> 30 | AG19: 1.53 | AH19: 1.74 | AL19: =AL18+1 -> 30 | AM19: 1.21 | AN19: 1.47 | AR19: 30 | AS19: 25.5 | AT19: 23.17 | AW19: =IF($AV$3=AR19,$AV$5*AS19,"") | AY19: =IF($AX$3=AR19,$AX$5*AT19,"")
A20: 31 | B20: 37.47 | C20: 33.78 | F20: =IF($E$3=A20,$E$5*B20,"") | H20: =IF($G$3=A20,$G$5*C20,"") | O20: =O19+1 -> 31 | P20: 0.59 | Q20: 0.59 | R20: =P20-Q20 -> 0 | T20: =IF($S$3=O20,$S$5*P20,"") | V20: =IF($U$3=O20,$U$5*Q20,"") | AC20: =IF($AB$3=AF20,$AB$5*AG20,"") | AE20: =IF($AD$3=AF20,$AD$5*AH20,"") | AF20: =AF19+1 -> 31 | AG20: 1.65 | AH20: 1.93 | AL20: =AL19+1 -> 31 | AM20: 1.33 | AN20: 1.66 | AR20: 31 | AS20: 26.2 | AT20: 23.5 | AW20: =IF($AV$3=AR20,$AV$5*AS20,"") | AY20: =IF($AX$3=AR20,$AX$5*AT20,"")
A21: 32 | B21: 38.46 | C21: 34.68 | F21: =IF($E$3=A21,$E$5*B21,"") | H21: =IF($G$3=A21,$G$5*C21,"") | O21: =O20+1 -> 32 | P21: 0.62 | Q21: 0.63 | R21: =P21-Q21 -> -0.01 | T21: =IF($S$3=O21,$S$5*P21,"") | V21: =IF($U$3=O21,$U$5*Q21,"") | AC21: =IF($AB$3=AF21,$AB$5*AG21,"") | AE21: =IF($AD$3=AF21,$AD$5*AH21,"") | AF21: =AF20+1 -> 32 | AG21: 1.78 | AH21: 2.13 | AL21: =AL20+1 -> 32 | AM21: 1.46 | AN21: 1.85 | AR21: 32 | AS21: 26.92 | AT21: 23.99 | AW21: =IF($AV$3=AR21,$AV$5*AS21,"") | AY21: =IF($AX$3=AR21,$AX$5*AT21,"")
A22: 33 | B22: 39.49 | C22: 35.61 | F22: =IF($E$3=A22,$E$5*B22,"") | H22: =IF($G$3=A22,$G$5*C22,"") | O22: =O21+1 -> 33 | P22: 0.66 | Q22: 0.66 | R22: =P22-Q22 -> 0 | T22: =IF($S$3=O22,$S$5*P22,"") | V22: =IF($U$3=O22,$U$5*Q22,"") | AC22: =IF($AB$3=AF22,$AB$5*AG22,"") | AE22: =IF($AD$3=AF22,$AD$5*AH22,"") | AF22: =AF21+1 -> 33 | AG22: 1.95 | AH22: 2.35 | AL22: =AL21+1 -> 33 | AM22: 1.62 | AN22: 2.07 | AR22: 33 | AS22: 27.67 | AT22: 24.5 | AW22: =IF($AV$3=AR22,$AV$5*AS22,"") | AY22: =IF($AX$3=AR22,$AX$5*AT22,"")
A23: 34 | B23: 40.54 | C23: 35.98 | F23: =IF($E$3=A23,$E$5*B23,"") | H23: =IF($G$3=A23,$G$5*C23,"") | O23: =O22+1 -> 34 | P23: 0.69 | Q23: 0.69 | R23: =P23-Q23 -> 0 | T23: =IF($S$3=O23,$S$5*P23,"") | V23: =IF($U$3=O23,$U$5*Q23,"") | AC23: =IF($AB$3=AF23,$AB$5*AG23,"") | AE23: =IF($AD$3=AF23,$AD$5*AH23,"") | AF23: =AF22+1 -> 34 | AG23: 2.13 | AH23: 2.6 | AL23: =AL22+1 -> 34 | AM23: 1.81 | AN23: 2.32 | AR23: 34 | AS23: 28.45 | AT23: 25.02 | AW23: =IF($AV$3=AR23,$AV$5*AS23,"") | AY23: =IF($AX$3=AR23,$AX$5*AT23,"")
A24: 35 | B24: 40.98 | C24: 36.37 | F24: =IF($E$3=A24,$E$5*B24,"") | H24: =IF($G$3=A24,$G$5*C24,"") | O24: =O23+1 -> 35 | P24: 0.72 | Q24: 0.72 | R24: =P24-Q24 -> 0 | T24: =IF($S$3=O24,$S$5*P24,"") | V24: =IF($U$3=O24,$U$5*Q24,"") | AC24: =IF($AB$3=AF24,$AB$5*AG24,"") | AE24: =IF($AD$3=AF24,$AD$5*AH24,"") | AF24: =AF23+1 -> 35 | AG24: 2.35 | AH24: 2.86 | AL24: =AL23+1 -> 35 | AM24: 2.02 | AN24: 2.58 | AR24: 35 | AS24: 28.89 | AT24: 25.39 | AW24: =IF($AV$3=AR24,$AV$5*AS24,"") | AY24: =IF($AX$3=AR24,$AX$5*AT24,"")
... A54: 65 | B54: 89.22 | C54: 76.56 | F54: =IF($E$3=A54,$E$5*B54,"") | H54: =IF($G$3=A54,$G$5*C54,"") | O54: =O53+1 -> 65 | P54: 2.82 | Q54: 2.83 | R54: =P54-Q54 -> -0.01 | T54: =IF($S$3=O54,$S$5*P54,"") | V54: =IF($U$3=O54,$U$5*Q54,"") | AC54: =IF($AB$3=AF54,$AB$5*AG54,"") | AE54: =IF($AD$3=AF54,$AD$5*AH54,"") | AF54: =AF53+1 -> 65 | AG54: 42.25 | AH54: 30.45 | AL54: =AL53+1 -> 65 | AM54: 39.47 | AN54: 28.95 | AR54: 65 | AS54: 74.27 | AT54: 62.09 | AW54: =IF($AV$3=AR54,$AV$5*AS54,"") | AY54: =IF($AX$3=AR54,$AX$5*AT54,"")
AR55: 66 | AW55: =IF($AV$3=AR55,$AV$5*AS55,"") | AY55: =IF($AX$3=AR55,$AX$5*AT55,"")
AR56: 67 | AW56: =IF($AV$3=AR56,$AV$5*AS56,"") | AY56: =IF($AX$3=AR56,$AX$5*AT56,"")
AR57: 68 | AW57: =IF($AV$3=AR57,$AV$5*AS57,"") | AY57: =IF($AX$3=AR57,$AX$5*AT57,"")
AR58: 69 | AW58: =IF($AV$3=AR58,$AV$5*AS58,"") | AY58: =IF($AX$3=AR58,$AX$5*AT58,"")
AR59: 70 | AW59: =IF($AV$3=AR59,$AV$5*AS59,"") | AY59: =IF($AX$3=AR59,$AX$5*AT59,"")
AR60: 71 | AW60: =IF($AV$3=AR60,$AV$5*AS60,"") | AY60: =IF($AX$3=AR60,$AX$5*AT60,"")
AR61: 72 | AW61: =IF($AV$3=AR61,$AV$5*AS61,"") | AY61: =IF($AX$3=AR61,$AX$5*AT61,"")
AR62: 73 | AW62: =IF($AV$3=AR62,$AV$5*AS62,"") | AY62: =IF($AX$3=AR62,$AX$5*AT62,"")
AR63: 74 | AW63: =IF($AV$3=AR63,$AV$5*AS63,"") | AY63: =IF($AX$3=AR63,$AX$5*AT63,"")
AR64: 75 | AW64: =IF($AV$3=AR64,$AV$5*AS64,"") | AY64: =IF($AX$3=AR64,$AX$5*AT64,"")

Sheet Resgate
D1: 1 | E1: 14 | F1: 15 | G1: 16 | H1: 17 | I1: 18 | J1: 19 | K1: 20 | L1: 21 | M1: 22 | N1: 23 | O1: 24 | P1: 25 | Q1: 26 | R1: 27 | S1: 28 | T1: 29 | U1: 30 | V1: 31 | W1: 32 | X1: 33 | Y1: 34 | Z1: 35 | AA1: 36 | AB1: 37 | AC1: 38 | AD1: 39 | AE1: 40 | AF1: 41 | AG1: 42 | AH1: 43 | AI1: 44 | AJ1: 45 | AK1: 46 | AL1: 47 | AM1: 48 | AN1: 49 | AO1: 50 | AP1: 51 | AQ1: 52 | AR1: 53 | AS1: 54 | AT1: 55 | AU1: 56 | AV1: 57 | AW1: 58 | AX1: 59 | AY1: 60 | AZ1: 61 | BA1: 62 | BB1: 63 | BC1: 64 | BD1: 65 | BF1: 14 | BG1: 15 | BH1: 16 | BI1: 17 | BJ1: 18 | BK1: 19 | BL1: 20 | BM1: 21 | BN1: 22 | BO1: 23 | BP1: 24 | BQ1: 25 | BR1: 26 | BS1: 27 | BT1: 28 | BU1: 29 | BV1: 30 | BW1: 31 | BX1: 32 | BY1: 33 | BZ1: 34 | CA1: 35 | CB1: 36 | CC1: 37 | CD1: 38 | CE1: 39 | CF1: 40 | CG1: 41 | CH1: 42 | CI1: 43 | CJ1: 44 | CK1: 45 | CL1: 46 | CM1: 47 | CN1: 48 | CO1: 49 | CP1: 50 | CQ1: 51 | CR1: 52 | CS1: 53 | CT1: 54 | CU1: 55 | CV1: 56 | CW1: 57 | CX1: 58 | CY1: 59 | CZ1: 60 | DA1: 61 | DB1: 62 | DC1: 63 | DD1: 64 | DE1: 65
A2: =Simulador!D14 -> 469.82357 | D2: 2 | E2: 0 | F2: 0 | G2: 0 | H2: 0 | I2: 0 | J2: 0 | K2: 0 | L2: 0 | M2: 0 | N2: 0 | O2: 0 | P2: 0 | Q2: 0 | R2: 0 | S2: 0 | T2: 0 | U2: 0 | V2: 0 | W2: 0 | X2: 0 | Y2: 0 | Z2: 0 | AA2: 0 | AB2: 0 | AC2: 0 | AD2: 0 | AE2: 0 | AF2: 0 | AG2: 0 | AH2: 0 | AI2: 0 | AJ2: 0 | AK2: 0 | AL2: 0 | AM2: 0 | AN2: 0 | AO2: 0 | AP2: 0 | AQ2: 0 | AR2: 0 | AS2: 0 | AT2: 0 | AU2: 0 | AV2: 0 | AW2: 0 | AX2: 0 | AY2: 0 | AZ2: 0 | BA2: 0 | BB2: 0 | BC2: 0 | BD2: 0 | BF2: 0 | BG2: 0 | BH2: 0 | BI2: 0 | BJ2: 0 | BK2: 0 | BL2: 0 | BM2: 0 | BN2: 0 | BO2: 0 | BP2: 0 | BQ2: 0 | BR2: 0 | BS2: 0 | BT2: 0 | BU2: 0 | BV2: 0 | BW2: 0 | BX2: 0 | BY2: 0 | BZ2: 0 | CA2: 0 | CB2: 0 | CC2: 0 | CD2: 0 | CE2: 0 | CF2: 0 | CG2: 0 | CH2: 0 | CI2: 0 | CJ2: 0 | CK2: 0 | CL2: 0 | CM2: 0 | CN2: 0 | CO2: 0 | CP2: 0 | CQ2: 0 | CR2: 0 | CS2: 0 | CT2: 0 | CU2: 0 | CV2: 0 | CW2: 0 | CX2: 0 | CY2: 0 | CZ2: 0 | DA2: 0 | DB2: 0 | DC2: 0 | DD2: 0 | DE2: 0
A3: =A2*(1+Simulador!$G$3) -> 495.66387 | D3: 3 | E3: 0 | F3: 0 | G3: 0 | H3: 0 | I3: 0 | J3: 0 | K3: 0 | L3: 0 | M3: 0 | N3: 0 | O3: 0 | P3: 0 | Q3: 0 | R3: 0 | S3: 0 | T3: 0 | U3: 0 | V3: 0 | W3: 0 | X3: 0 | Y3: 0 | Z3: 0 | AA3: 0 | AB3: 0 | AC3: 0 | AD3: 0 | AE3: 0 | AF3: 0 | AG3: 0 | AH3: 0 | AI3: 0 | AJ3: 0 | AK3: 0 | AL3: 0 | AM3: 0 | AN3: 0 | AO3: 0 | AP3: 0 | AQ3: 0 | AR3: 0 | AS3: 0 | AT3: 0 | AU3: 0 | AV3: 0 | AW3: 0 | AX3: 0 | AY3: 0 | AZ3: 0 | BA3: 0 | BB3: 0 | BC3: 0 | BD3: 0 | BF3: 0 | BG3: 0 | BH3: 0 | BI3: 0 | BJ3: 0 | BK3: 0 | BL3: 0 | BM3: 0 | BN3: 0 | BO3: 0 | BP3: 0 | BQ3: 0 | BR3: 0 | BS3: 0 | BT3: 0 | BU3: 0 | BV3: 0 | BW3: 0 | BX3: 0 | BY3: 0 | BZ3: 0 | CA3: 0 | CB3: 0 | CC3: 0 | CD3: 0 | CE3: 0 | CF3: 0 | CG3: 0 | CH3: 0 | CI3: 0 | CJ3: 0 | CK3: 0 | CL3: 0 | CM3: 0 | CN3: 0 | CO3: 0 | CP3: 0 | CQ3: 0 | CR3: 0 | CS3: 0 | CT3: 0 | CU3: 0 | CV3: 0 | CW3: 0 | CX3: 0 | CY3: 0 | CZ3: 0 | DA3: 0 | DB3: 0 | DC3: 0 | DD3: 0 | DE3: 0
A4: =A3*(1+Simulador!$G$3) -> 522.92538 | D4: 4 | E4: 0.01056 | F4: 0.01078 | G4: 0.01101 | H4: 0.01125 | I4: 0.01017 | J4: 0.0118 | K4: 0.0121 | L4: 0.01241 | M4: 0.01275 | N4: 0.0131 | O4: 0.01346 | P4: 0.01383 | Q4: 0.0142 | R4: 0.01459 | S4: 0.01498 | T4: 0.01538 | U4: 0.01578 | V4: 0.01619 | W4: 0.01661 | X4: 0.01703 | Y4: 0.01746 | Z4: 0.01789 | AA4: 0.01833 | AB4: 0.01877 | AC4: 0.01922 | AD4: 0.01966 | AE4: 0.02011 | AF4: 0.02056 | AG4: 0.02102 | AH4: 0.02148 | AI4: 0.02195 | AJ4: 0.02242 | AK4: 0.0229 | AL4: 0.02338 | AM4: 0.02387 | AN4: 0.02435 | AO4: 0.02482 | AP4: 0.02528 | AQ4: 0.02573 | AR4: 0.02617 | AS4: 0.0266 | AT4: 0.02703 | AU4: 0.02746 | AV4: 0.02789 | AW4: 0.02831 | AX4: 0.02871 | AY4: 0.02909 | AZ4: 0.02944 | BA4: 0.02975 | BB4: 0.03002 | BC4: 0.03028 | BD4: 0.03053 | BF4: 0.00926 | BG4: 0.0095 | BH4: 0.00974 | BI4: 0.00999 | BJ4: 0.01025 | BK4: 0.01051 | BL4: 0.01079 | BM4: 0.01108 | BN4: 0.01137 | BO4: 0.01167 | BP4: 0.01198 | BQ4: 0.01229 | BR4: 0.01262 | BS4: 0.01295 | BT4: 0.01329 | BU4: 0.01364 | BV4: 0.01399 | BW4: 0.01436 | BX4: 0.01473 | BY4: 0.01511 | BZ4: 0.0155 | CA4: 0.01589 | CB4: 0.01628 | CC4: 0.01667 | CD4: 0.01706 | CE4: 0.01745 | CF4: 0.01785 | CG4: 0.01826 | CH4: 0.01868 | CI4: 0.0191 | CJ4: 0.01953 | CK4: 0.01997 | CL4: 0.02042 | CM4: 0.02087 | CN4: 0.02133 | CO4: 0.02179 | CP4: 0.02225 | CQ4: 0.02271 | CR4: 0.02316 | CS4: 0.02363 | CT4: 0.0241 | CU4: 0.0246 | CV4: 0.02512 | CW4: 0.02566 | CX4: 0.0262 | CY4: 0.02675 | CZ4: 0.02727 | DA4: 0.02776 | DB4: 0.02821 | DC4: 0.02863 | DD4: 0.02905 | DE4: 0.02949
A5: =A4*(1+Simulador!$G$3) -> 551.68628 | D5: 5 | E5: 0.02663 | F5: 0.0272 | G5: 0.02779 | H5: 0.02844 | I5: 0.02912 | J5: 0.02985 | K5: 0.03061 | L5: 0.03142 | M5: 0.03227 | N5: 0.03314 | O5: 0.03405 | P5: 0.03497 | Q5: 0.03592 | R5: 0.03688 | S5: 0.03786 | T5: 0.03886 | U5: 0.03988 | V5: 0.04091 | W5: 0.04196 | X5: 0.04302 | Y5: 0.0441 | Z5: 0.04518 | AA5: 0.04628 | AB5: 0.04739 | AC5: 0.0485 | AD5: 0.04963 | AE5: 0.05076 | AF5: 0.0519 | AG5: 0.05306 | AH5: 0.05423 | AI5: 0.05541 | AJ5: 0.0566 | AK5: 0.05781 | AL5: 0.05903 | AM5: 0.06024 | AN5: 0.06144 | AO5: 0.06263 | AP5: 0.06378 | AQ5: 0.06491 | AR5: 0.06603 | AS5: 0.06623 | AT5: 0.06823 | AU5: 0.06932 | AV5: 0.07041 | AW5: 0.07147 | AX5: 0.07248 | AY5: 0.07342 | AZ5: 0.07428 | BA5: 0.07507 | BB5: 0.07579 | BC5: 0.07647 | BD5: 0.07714 | BF5: 0.02339 | BG5: 0.02399 | BH5: 0.0246 | BI5: 0.02523 | BJ5: 0.02589 | BK5: 0.02657 | BL5: 0.02727 | BM5: 0.02799 | BN5: 0.02873 | BO5: 0.02949 | BP5: 0.03026 | BQ5: 0.03106 | BR5: 0.03188 | BS5: 0.03272 | BT5: 0.03357 | BU5: 0.03445 | BV5: 0.03535 | BW5: 0.03628 | BX5: 0.03722 | BY5: 0.03817 | BZ5: 0.03914 | CA5: 0.04011 | CB5: 0.04108 | CC5: 0.04206 | CD5: 0.04305 | CE5: 0.04405 | CF5: 0.04506 | CG5: 0.0461 | CH5: 0.04715 | CI5: 0.04823 | CJ5: 0.04932 | CK5: 0.05044 | CL5: 0.05156 | CM5: 0.05271 | CN5: 0.05386 | CO5: 0.05502 | CP5: 0.05617 | CQ5: 0.05733 | CR5: 0.0585 | CS5: 0.05969 | CT5: 0.06092 | CU5: 0.0622 | CV5: 0.06352 | CW5: 0.06487 | CX5: 0.06624 | CY5: 0.06757 | CZ5: 0.06884 | DA5: 0.07004 | DB5: 0.07117 | DC5: 0.07227 | DD5: 0.07337 | DE5: 0.07453
A6: =A5*(1+Simulador!$G$3) -> 582.02902 | D6: 6 | E6: 0.05422 | F6: 0.05541 | G6: 0.05668 | H6: 0.05802 | I6: 0.05944 | J6: 0.06095 | K6: 0.06253 | L6: 0.06419 | M6: 0.06591 | N6: 0.06769 | O6: 0.06952 | P6: 0.07139 | Q6: 0.07331 | R6: 0.07526 | S6: 0.07724 | T6: 0.07927 | U6: 0.08133 | V6: 0.08342 | W6: 0.08555 | X6: 0.0877 | Y6: 0.08988 | Z6: 0.09209 | AA6: 0.09431 | AB6: 0.09656 | AC6: 0.09883 | AD6: 0.10112 | AE6: 0.10343 | AF6: 0.10577 | AG6: 0.10813 | AH6: 0.11051 | AI6: 0.11293 | AJ6: 0.11537 | AK6: 0.11783 | AL6: 0.1203 | AM6: 0.12276 | AN6: 0.12519 | AO6: 0.12758 | AP6: 0.12994 | AQ6: 0.13226 | AR6: 0.13456 | AS6: 0.13684 | AT6: 0.13911 | AU6: 0.14137 | AV6: 0.14087 | AW6: 0.14573 | AX6: 0.14777 | AY6: 0.14968 | AZ6: 0.15145 | BA6: 0.1531 | BB6: 0.15466 | BC6: 0.15615 | BD6: 0.15758 | BF6: 0.04769 | BG6: 0.04891 | BH6: 0.05016 | BI6: 0.05146 | BJ6: 0.05281 | BK6: 0.05419 | BL6: 0.05562 | BM6: 0.05709 | BN6: 0.0586 | BO6: 0.06014 | BP6: 0.06173 | BQ6: 0.06335 | BR6: 0.06502 | BS6: 0.06672 | BT6: 0.06847 | BU6: 0.07026 | BV6: 0.0721 | BW6: 0.07397 | BX6: 0.07588 | BY6: 0.07781 | BZ6: 0.07976 | CA6: 0.08172 | CB6: 0.0837 | CC6: 0.08569 | CD6: 0.08771 | CE6: 0.08975 | CF6: 0.09183 | CG6: 0.09395 | CH6: 0.09611 | CI6: 0.09831 | CJ6: 0.10055 | CK6: 0.10282 | CL6: 0.10512 | CM6: 0.10745 | CN6: 0.10979 | CO6: 0.11215 | CP6: 0.11451 | CQ6: 0.1169 | CR6: 0.11932 | CS6: 0.12179 | CT6: 0.12435 | CU6: 0.12698 | CV6: 0.13468 | CW6: 0.13241 | CX6: 0.13513 | CY6: 0.13777 | CZ6: 0.1403 | DA6: 0.14273 | DB6: 0.14507 | DC6: 0.14739 | DD6: 0.14975 | DE6: 0.15218
A7: =A6*(1+Simulador!$G$3) -> 614.04062 | D7: 7 | E7: 0.08064 | F7: 0.08248 | G7: 0.08442 | H7: 0.08646 | I7: 0.08862 | J7: 0.09089 | K7: 0.09326 | L7: 0.09573 | M7: 0.09829 | N7: 0.10092 | O7: 0.10363 | P7: 0.1064 | Q7: 0.10922 | R7: 0.11211 | S7: 0.11505 | T7: 0.11805 | U7: 0.1211 | V7: 0.1242 | W7: 0.12734 | X7: 0.13053 | Y7: 0.13376 | Z7: 0.13703 | AA7: 0.14033 | AB7: 0.14367 | AC7: 0.14705 | AD7: 0.15045 | AE7: 0.1539 | AF7: 0.15739 | AG7: 0.16091 | AH7: 0.16448 | AI7: 0.16808 | AJ7: 0.17172 | AK7: 0.17537 | AL7: 0.17903 | AM7: 0.18267 | AN7: 0.18628 | AO7: 0.18984 | AP7: 0.19337 | AQ7: 0.19686 | AR7: 0.20033 | AS7: 0.20379 | AT7: 0.20721 | AU7: 0.21059 | AV7: 0.2139 | AW7: 0.21709 | AX7: 0.22014 | AY7: 0.22303 | AZ7: 0.22576 | BA7: 0.22834 | BB7: 0.23081 | BC7: 0.23316 | BD7: 0.2354 | BF7: 0.07098 | BG7: 0.07281 | BH7: 0.07469 | BI7: 0.07664 | BJ7: 0.07864 | BK7: 0.08071 | BL7: 0.08283 | BM7: 0.08502 | BN7: 0.08726 | BO7: 0.08956 | BP7: 0.09192 | BQ7: 0.09434 | BR7: 0.09682 | BS7: 0.09936 | BT7: 0.10196 | BU7: 0.10462 | BV7: 0.10735 | BW7: 0.11012 | BX7: 0.11293 | BY7: 0.11578 | BZ7: 0.11867 | CA7: 0.12157 | CB7: 0.12451 | CC7: 0.12748 | CD7: 0.13049 | CE7: 0.13354 | CF7: 0.13665 | CG7: 0.13982 | CH7: 0.14305 | CI7: 0.14634 | CJ7: 0.14967 | CK7: 0.15306 | CL7: 0.15649 | CM7: 0.15995 | CN7: 0.16344 | CO7: 0.16695 | CP7: 0.1705 | CQ7: 0.1741 | CR7: 0.17776 | CS7: 0.18151 | CT7: 0.18537 | CU7: 0.18931 | CV7: 0.19331 | CW7: 0.19732 | CX7: 0.20127 | CY7: 0.20513 | CZ7: 0.20888 | DA7: 0.21252 | DB7: 0.21611 | DC7: 0.21971 | DD7: 0.22335 | DE7: 0.22703
A8: =A7*(1+Simulador!$G$3) -> 647.81285 | D8: 8 | E8: 0.11283 | F8: 0.11547 | G8: 0.11825 | H8: 0.12117 | I8: 0.12423 | J8: 0.12743 | K8: 0.13076 | L8: 0.13421 | M8: 0.13778 | N8: 0.14144 | O8: 0.1452 | P8: 0.14905 | Q8: 0.15298 | R8: 0.157 | S8: 0.16109 | T8: 0.16527 | U8: 0.16951 | V8: 0.17382 | W8: 0.17821 | X8: 0.18265 | Y8: 0.18716 | Z8: 0.19171 | AA8: 0.19633 | AB8: 0.20099 | AC8: 0.20572 | AD8: 0.2105 | AE8: 0.21533 | AF8: 0.22022 | AG8: 0.22518 | AH8: 0.23019 | AI8: 0.23525 | AJ8: 0.24033 | AK8: 0.24544 | AL8: 0.25054 | AM8: 0.25563 | AN8: 0.26068 | AO8: 0.2657 | AP8: 0.27069 | AQ8: 0.27565 | AR8: 0.28059 | AS8: 0.2855 | AT8: 0.29036 | AU8: 0.29514 | AV8: 0.2998 | AW8: 0.30432 | AX8: 0.30867 | AY8: 0.31285 | AZ8: 0.31685 | BA8: 0.3207 | BB8: 0.32439 | BC8: 0.3279 | BD8: 0.3312 | BF8: 0.09935 | BG8: 0.10192 | BH8: 0.10457 | BI8: 0.10731 | BJ8: 0.11011 | BK8: 0.11301 | BL8: 0.11599 | BM8: 0.11904 | BN8: 0.12218 | BO8: 0.1254 | BP8: 0.12869 | BQ8: 0.13208 | BR8: 0.13555 | BS8: 0.1391 | BT8: 0.14273 | BU8: 0.14645 | BV8: 0.15024 | BW8: 0.1541 | BX8: 0.15801 | BY8: 0.16198 | BZ8: 0.16599 | CA8: 0.17004 | CB8: 0.17415 | CC8: 0.17831 | CD8: 0.18254 | CE8: 0.18684 | CF8: 0.19122 | CG8: 0.19568 | CH8: 0.20021 | CI8: 0.20482 | CJ8: 0.2095 | CK8: 0.21425 | CL8: 0.21905 | CM8: 0.22389 | CN8: 0.22878 | CO8: 0.23373 | CP8: 0.23875 | CQ8: 0.24386 | CR8: 0.24908 | CS8: 0.25442 | CT8: 0.25986 | CU8: 0.26538 | CV8: 0.27093 | CW8: 0.27646 | CX8: 0.28191 | CY8: 0.28728 | CZ8: 0.29256 | DA8: 0.29779 | DB8: 0.303 | DC8: 0.30822 | DD8: 0.31345 | DE8: 0.31865
A9: =A8*(1+Simulador!$G$3) -> 683.44256 | D9: 9 | E9: 0.15105 | F9: 0.15468 | G9: 0.158245 | H9: 0.16244 | I9: 0.16658 | J9: 0.17088 | K9: 0.17534 | L9: 0.17995 | M9: 0.1847 | N9: 0.18958 | O9: 0.19458 | P9: 0.1997 | Q9: 0.20493 | R9: 0.21028 | S9: 0.21573 | T9: 0.22128 | U9: 0.2269 | V9: 0.2327 | W9: 0.23854 | X9: 0.24446 | Y9: 0.25047 | Z9: 0.25656 | AA9: 0.26273 | AB9: 0.26898 | AC9: 0.27532 | AD9: 0.28173 | AE9: 0.28822 | AF9: 0.2948 | AG9: 0.30146 | AH9: 0.30819 | AI9: 0.31497 | AJ9: 0.32178 | AK9: 0.32861 | AL9: 0.33545 | AM9: 0.34227 | AN9: 0.34908 | AO9: 0.35588 | AP9: 0.36266 | AQ9: 0.36942 | AR9: 0.37615 | AS9: 0.38283 | AT9: 0.38943 | AU9: 0.39593 | AV9: 0.40229 | AW9: 0.40849 | AX9: 0.41452 | AY9: 0.42038 | AZ9: 0.42607 | BA9: 0.43158 | BB9: 0.43688 | BC9: 0.44193 | BD9: 0.44666 | BF9: 0.13302 | BG9: 0.13648 | BH9: 0.14004 | BI9: 0.1437 | BJ9: 0.14747 | BK9: 0.15135 | BL9: 0.15533 | BM9: 0.15942 | BN9: 0.16362 | BO9: 0.16792 | BP9: 0.17234 | BQ9: 0.17687 | BR9: 0.1815 | BS9: 0.18625 | BT9: 0.19111 | BU9: 0.19607 | BV9: 0.20112 | BW9: 0.20625 | BX9: 0.21146 | BY9: 0.21674 | BZ9: 0.22209 | CA9: 0.22751 | CB9: 0.23301 | CC9: 0.2386 | CD9: 0.24429 | CE9: 0.25008 | CF9: 0.25596 | CG9: 0.26195 | CH9: 0.26804 | CI9: 0.27423 | CJ9: 0.28051 | CK9: 0.28687 | CL9: 0.2933 | CM9: 0.29981 | CN9: 0.30641 | CO9: 0.3131 | CP9: 0.31991 | CQ9: 0.32686 | CR9: 0.03335 | CS9: 0.34117 | CT9: 0.34849 | CU9: 0.35586 | CV9: 0.36323 | CW9: 0.37056 | CX9: 0.37785 | CY9: 0.38509 | CZ9: 0.39231 | DA9: 0.39952 | DB9: 0.40673 | DC9: 0.41393 | DD9: 0.42108 | DE9: 0.42809
A10: =A9*(1+Simulador!$G$3) -> 721.0319 | D10: 10 | E10: 0.19561 | F10: 0.2004 | G10: 0.20539 | H10: 0.21059 | I10: 0.21598 | J10: 0.22156 | K10: 0.22733 | L10: 0.23328 | M10: 0.23939 | N10: 0.24567 | O10: 0.2521 | P10: 0.25869 | Q10: 0.26543 | R10: 0.27232 | S10: 0.27934 | T10: 0.2865 | U10: 0.29379 | V10: 0.30121 | W10: 0.30874 | X10: 0.31639 | Y10: 0.32416 | Z10: 0.33203 | AA10: 0.34002 | AB10: 0.34813 | AC10: 0.35634 | AD10: 0.36468 | AE10: 0.37312 | AF10: 0.38168 | AG10: 0.39033 | AH10: 0.39906 | AI10: 0.40785 | AJ10: 0.41669 | AK10: 0.42556 | AL10: 0.43444 | AM10: 0.44334 | AN10: 0.45226 | AO10: 0.46119 | AP10: 0.37012 | AQ10: 0.47904 | AR10: 0.48793 | AS10: 0.49675 | AT10: 0.50548 | AU10: 0.51408 | AV10: 0.52256 | AW10: 0.5309 | AX10: 0.5391 | AY10: 0.54716 | AZ10: 0.55505 | BA10: 0.56274 | BB10: 0.57017 | BC10: 0.57728 | BD10: 0.58402 | BF10: 0.17222 | BG10: 0.17672 | BH10: 0.18134 | BI10: 0.18609 | BJ10: 0.19098 | BK10: 0.196 | BL10: 0.20115 | BM10: 0.20644 | BN10: 0.21187 | BO10: 0.21744 | BP10: 0.22316 | BQ10: 0.22901 | BR10: 0.23501 | BS10: 0.24115 | BT10: 0.24742 | BU10: 0.25381 | BV10: 0.26031 | BW10: 0.26691 | BX10: 0.27362 | BY10: 0.28043 | BZ10: 0.28734 | CA10: 0.29437 | CB10: 0.30151 | CC10: 0.30877 | CD10: 0.31617 | CE10: 0.3237 | CF10: 0.33135 | CG10: 0.33914 | CH10: 0.34705 | CI10: 0.35508 | CJ10: 0.36323 | CK10: 0.37148 | CL10: 0.37984 | CM10: 0.38832 | CN10: 0.39693 | CO10: 0.40571 | CP10: 0.41466 | CQ10: 0.42379 | CR10: 0.43307 | CS10: 0.44249 | CT10: 0.45197 | CU10: 0.46148 | CV10: 0.471 | CW10: 0.48052 | CX10: 0.49003 | CY10: 0.49958 | CZ10: 0.50918 | DA10: 0.51881 | DB10: 0.52845 | DC10: 0.53803 | DD10: 0.54747 | DE10: 0.5567
A11: =A10*(1+Simulador!$G$3) -> 760.68865 | D11: 11 | E11: 0.2598 | F11: 0.26627 | G11: 0.27299 | H11: 0.27994 | I11: 0.28712 | J11: 0.29453 | K11: 0.30216 | L11: 0.31002 | M11: 0.3181 | N11: 0.32638 | O11: 0.33487 | P11: 0.34357 | Q11: 0.35248 | R11: 0.36157 | S11: 0.37085 | T11: 0.38031 | U11: 0.38995 | V11: 0.39976 | W11: 0.40974 | X11: 0.41988 | Y11: 0.43018 | Z11: 0.43018 | AA11: 0.45126 | AB11: 0.46204 | AC11: 0.47299 | AD11: 0.4841 | AE11: 0.49536 | AF11: 0.50677 | AG11: 0.5183 | AH11: 0.52993 | AI11: 0.54165 | AJ11: 0.55343 | AK11: 0.56526 | AL11: 0.57716 | AM11: 0.58912 | AN11: 0.60114 | AO11: 0.6132 | AP11: 0.62531 | AQ11: 0.63741 | AR11: 0.64948 | AS11: 0.66148 | AT11: 0.6734 | AU11: 0.68522 | AV11: 0.69695 | AW11: 0.7086 | AX11: 0.72016 | AY11: 0.73162 | AZ11: 0.74293 | BA11: 0.75405 | BB11: 0.76489 | BC11: 0.77541 | BD11: 0.78557 | BF11: 0.22865 | BG11: 0.23462 | BH11: 0.24078 | BI11: 0.24709 | BJ11: 0.25358 | BK11: 0.26024 | BL11: 0.26708 | BM11: 0.2741 | BN11: 0.2813 | BO11: 0.2887 | BP11: 0.29627 | BQ11: 0.30404 | BR11: 0.31199 | BS11: 0.32012 | BT11: 0.3284 | BU11: 0.33684 | BV11: 0.34543 | BW11: 0.35416 | BX11: 0.36303 | BY11: 0.37205 | BZ11: 0.38123 | CA11: 0.39057 | CB11: 0.40008 | CC11: 0.40977 | CD11: 0.41963 | CE11: 0.42967 | CF11: 0.43987 | CG11: 0.45025 | CH11: 0.46079 | CI11: 0.47149 | CJ11: 0.48233 | CK11: 0.49333 | CL11: 0.50449 | CM11: 0.51585 | CN11: 0.52743 | CO11: 0.53924 | CP11: 0.55129 | CQ11: 0.56355 | CR11: 0.57599 | CS11: 0.58854 | CT11: 0.60116 | CU11: 0.61382 | CV11: 0.62653 | CW11: 0.6393 | CX11: 0.65217 | CY11: 0.66517 | CZ11: 0.6783 | DA11: 0.6915 | DB11: 0.70471 | DC11: 0.71782 | DD11: 0.73074 | DE11: 0.74341
D12: 12 | E12: 0.26627 | F12: 0.27299 | G12: 0.27994 | H12: 0.28712 | I12: 0.29453 | J12: 0.30216 | K12: 0.31002 | L12: 0.3181 | M12: 0.32638 | N12: 0.33487 | O12: 0.34357 | P12: 0.35248 | Q12: 0.36157 | R12: 0.37085 | S12: 0.38031 | T12: 0.38995 | U12: 0.39976 | V12: 0.40974 | W12: 0.41988 | X12: 0.43018 | Y12: 0.44064 | Z12: 0.45126 | AA12: 0.46204 | AB12: 0.47299 | AC12: 0.4841 | AD12: 0.49536 | AE12: 0.50677 | AF12: 0.5183 | AG12: 0.52993 | AH12: 0.54165 | AI12: 0.55343 | AJ12: 0.56526 | AK12: 0.57716 | AL12: 0.58912 | AM12: 0.60114 | AN12: 0.6132 | AO12: 0.62531 | AP12: 0.63741 | AQ12: 0.64948 | AR12: 0.66148 | AS12: 0.6734 | AT12: 0.68522 | AU12: 0.69695 | AV12: 0.7086 | AW12: 0.72016 | AX12: 0.73162 | AY12: 0.74293 | AZ12: 0.75405 | BA12: 0.76489 | BB12: 0.77541 | BC12: 0.78557 | BD12: 0.79538 | BF12: 0.23462 | BG12: 0.24078 | BH12: 0.24709 | BI12: 0.25358 | BJ12: 0.26024 | BK12: 0.26708 | BL12: 0.2741 | BM12: 0.2813 | BN12: 0.2887 | BO12: 0.29627 | BP12: 0.30404 | BQ12: 0.31199 | BR12: 0.32012 | BS12: 0.3284 | BT12: 0.33684 | BU12: 0.34543 | BV12: 0.35416 | BW12: 0.36303 | BX12: 0.37205 | BY12: 0.38123 | BZ12: 0.39057 | CA12: 0.40008 | CB12: 0.40977 | CC12: 0.41963 | CD12: 0.42967 | CE12: 0.43987 | CF12: 0.45025 | CG12: 0.46079 | CH12: 0.47149 | CI12: 0.48233 | CJ12: 0.49333 | CK12: 0.50449 | CL12: 0.51585 | CM12: 0.52743 | CN12: 0.53924 | CO12: 0.55129 | CP12: 0.56355 | CQ12: 0.57599 | CR12: 0.58854 | CS12: 0.60116 | CT12: 0.61382 | CU12: 0.62653 | CV12: 0.6393 | CW12: 0.65217 | CX12: 0.66517 | CY12: 0.6783 | CZ12: 0.6915 | DA12: 0.70471 | DB12: 0.71782 | DC12: 0.73074 | DD12: 0.74341 | DE12: 0.75581
D13: 13 | E13: 0.27299 | F13: 0.27994 | G13: 0.28712 | H13: 0.29453 | I13: 0.30216 | J13: 0.31002 | K13: 0.3181 | L13: 0.32638 | M13: 0.33487 | N13: 0.34357 | O13: 0.35248 | P13: 0.36157 | Q13: 0.37085 | R13: 0.38031 | S13: 0.38995 | T13: 0.39976 | U13: 0.40974 | V13: 0.41988 | W13: 0.43018 | X13: 0.44064 | Y13: 0.45126 | Z13: 0.46204 | AA13: 0.47299 | AB13: 0.4841 | AC13: 0.49536 | AD13: 0.50677 | AE13: 0.5183 | AF13: 0.52993 | AG13: 0.54165 | AH13: 0.55343 | AI13: 0.56526 | AJ13: 0.57716 | AK13: 0.58912 | AL13: 0.60114 | AM13: 0.6132 | AN13: 0.62531 | AO13: 0.63741 | AP13: 0.64948 | AQ13: 0.66148 | AR13: 0.6734 | AS13: 0.68522 | AT13: 0.69695 | AU13: 0.7086 | AV13: 0.72016 | AW13: 0.73162 | AX13: 0.74293 | AY13: 0.75405 | AZ13: 0.76489 | BA13: 0.77541 | BB13: 0.78557 | BC13: 0.79538 | BD13: 0.80486 | BF13: 0.24078 | BG13: 0.24709 | BH13: 0.25358 | BI13: 0.26024 | BJ13: 0.26708 | BK13: 0.2741 | BL13: 0.2813 | BM13: 0.2887 | BN13: 0.29627 | BO13: 0.30404 | BP13: 0.31199 | BQ13: 0.32012 | BR13: 0.3284 | BS13: 0.33684 | BT13: 0.34543 | BU13: 0.35416 | BV13: 0.36303 | BW13: 0.37205 | BX13: 0.38123 | BY13: 0.39057 | BZ13: 0.40008 | CA13: 0.40977 | CB13: 0.41963 | CC13: 0.42967 | CD13: 0.43987 | CE13: 0.45025 | CF13: 0.46079 | CG13: 0.47149 | CH13: 0.48233 | CI13: 0.49333 | CJ13: 0.50449 | CK13: 0.51585 | CL13: 0.52743 | CM13: 0.53924 | CN13: 0.55129 | CO13: 0.56355 | CP13: 0.57599 | CQ13: 0.58854 | CR13: 0.60116 | CS13: 0.61382 | CT13: 0.62653 | CU13: 0.6393 | CV13: 0.65217 | CW13: 0.66517 | CX13: 0.6783 | CY13: 0.6915 | CZ13: 0.70471 | DA13: 0.71782 | DB13: 0.73074 | DC13: 0.74341 | DD13: 0.75581 | DE13: 0.76794
D14: 14 | E14: 0.27994 | F14: 0.28712 | G14: 0.29453 | H14: 0.30216 | I14: 0.31002 | J14: 0.3181 | K14: 0.32638 | L14: 0.33487 | M14: 0.34357 | N14: 0.35248 | O14: 0.36157 | P14: 0.37085 | Q14: 0.38031 | R14: 0.38995 | S14: 0.39976 | T14: 0.40974 | U14: 0.41988 | V14: 0.43018 | W14: 0.44064 | X14: 0.45126 | Y14: 0.46204 | Z14: 0.47299 | AA14: 0.4841 | AB14: 0.49536 | AC14: 0.50677 | AD14: 0.5183 | AE14: 0.52993 | AF14: 0.54165 | AG14: 0.55343 | AH14: 0.56526 | AI14: 0.57716 | AJ14: 0.58912 | AK14: 0.60114 | AL14: 0.6132 | AM14: 0.62531 | AN14: 0.63741 | AO14: 0.64948 | AP14: 0.66148 | AQ14: 0.6734 | AR14: 0.68522 | AS14: 0.69695 | AT14: 0.7086 | AU14: 0.72016 | AV14: 0.73162 | AW14: 0.74293 | AX14: 0.75405 | AY14: 0.76489 | AZ14: 0.77541 | BA14: 0.78557 | BB14: 0.79538 | BC14: 0.80486 | BD14: 0.81406 | BF14: 0.24709 | BG14: 0.25358 | BH14: 0.26024 | BI14: 0.26708 | BJ14: 0.2741 | BK14: 0.2813 | BL14: 0.2887 | BM14: 0.29627 | BN14: 0.30404 | BO14: 0.31199 | BP14: 0.32012 | BQ14: 0.3284 | BR14: 0.33684 | BS14: 0.34543 | BT14: 0.35416 | BU14: 0.36303 | BV14: 0.37205 | BW14: 0.38123 | BX14: 0.39057 | BY14: 0.40008 | BZ14: 0.40977 | CA14: 0.41963 | CB14: 0.42967 | CC14: 0.43987 | CD14: 0.45025 | CE14: 0.46079 | CF14: 0.47149 | CG14: 0.48233 | CH14: 0.49333 | CI14: 0.50449 | CJ14: 0.51585 | CK14: 0.52743 | CL14: 0.53924 | CM14: 0.55129 | CN14: 0.56355 | CO14: 0.57599 | CP14: 0.58854 | CQ14: 0.60116 | CR14: 0.61382 | CS14: 0.62653 | CT14: 0.6393 | CU14: 0.65217 | CV14: 0.66517 | CW14: 0.6783 | CX14: 0.6915 | CY14: 0.70471 | CZ14: 0.71782 | DA14: 0.73074 | DB14: 0.74341 | DC14: 0.75581 | DD14: 0.76794 | DE14: 0.77981
D15: 15 | E15: 0.28712 | F15: 0.29453 | G15: 0.30216 | H15: 0.31002 | I15: 0.3181 | J15: 0.32638 | K15: 0.33487 | L15: 0.34357 | M15: 0.35248 | N15: 0.36157 | O15: 0.37085 | P15: 0.38031 | Q15: 0.38995 | R15: 0.39976 | S15: 0.40974 | T15: 0.41988 | U15: 0.43018 | V15: 0.44064 | W15: 0.45126 | X15: 0.46204 | Y15: 0.47299 | Z15: 0.4841 | AA15: 0.49536 | AB15: 0.50677 | AC15: 0.5183 | AD15: 0.52993 | AE15: 0.54165 | AF15: 0.55343 | AG15: 0.56526 | AH15: 0.57716 | AI15: 0.58912 | AJ15: 0.60114 | AK15: 0.6132 | AL15: 0.62531 | AM15: 0.63741 | AN15: 0.64948 | AO15: 0.66148 | AP15: 0.6734 | AQ15: 0.68522 | AR15: 0.69695 | AS15: 0.7086 | AT15: 0.72016 | AU15: 0.73162 | AV15: 0.74293 | AW15: 0.75405 | AX15: 0.76489 | AY15: 0.77541 | AZ15: 0.78557 | BA15: 0.79538 | BB15: 0.80486 | BC15: 0.81406 | BD15: 0.82303 | BF15: 0.25358 | BG15: 0.26024 | BH15: 0.26708 | BI15: 0.2741 | BJ15: 0.2813 | BK15: 0.2887 | BL15: 0.29627 | BM15: 0.30404 | BN15: 0.31199 | BO15: 0.32012 | BP15: 0.3284 | BQ15: 0.33684 | BR15: 0.34543 | BS15: 0.35416 | BT15: 0.36303 | BU15: 0.37205 | BV15: 0.38123 | BW15: 0.39057 | BX15: 0.40008 | BY15: 0.40977 | BZ15: 0.41963 | CA15: 0.42967 | CB15: 0.43987 | CC15: 0.45025 | CD15: 0.46079 | CE15: 0.47149 | CF15: 0.48233 | CG15: 0.49333 | CH15: 0.50449 | CI15: 0.51585 | CJ15: 0.52743 | CK15: 0.53924 | CL15: 0.55129 | CM15: 0.56355 | CN15: 0.57599 | CO15: 0.58854 | CP15: 0.60116 | CQ15: 0.61382 | CR15: 0.62653 | CS15: 0.6393 | CT15: 0.65217 | CU15: 0.66517 | CV15: 0.6783 | CW15: 0.6915 | CX15: 0.70471 | CY15: 0.71782 | CZ15: 0.73074 | DA15: 0.74341 | DB15: 0.75581 | DC15: 0.76794 | DD15: 0.77981 | DE15: 0.79146
D16: 16 | E16: 0.29453 | F16: 0.30216 | G16: 0.31002 | H16: 0.3181 | I16: 0.32638 | J16: 0.33487 | K16: 0.34357 | L16: 0.35248 | M16: 0.36157 | N16: 0.37085 | O16: 0.38031 | P16: 0.38995 | Q16: 0.39976 | R16: 0.40974 | S16: 0.41988 | T16: 0.43018 | U16: 0.44064 | V16: 0.45126 | W16: 0.46204 | X16: 0.47299 | Y16: 0.4841 | Z16: 0.49536 | AA16: 0.50677 | AB16: 0.5183 | AC16: 0.52993 | AD16: 0.54165 | AE16: 0.55343 | AF16: 0.56526 | AG16: 0.57716 | AH16: 0.58912 | AI16: 0.60114 | AJ16: 0.6132 | AK16: 0.62531 | AL16: 0.63741 | AM16: 0.64948 | AN16: 0.66148 | AO16: 0.6734 | AP16: 0.68522 | AQ16: 0.69695 | AR16: 0.7086 | AS16: 0.72016 | AT16: 0.73162 | AU16: 0.74293 | AV16: 0.75405 | AW16: 0.76489 | AX16: 0.77541 | AY16: 0.78557 | AZ16: 0.79538 | BA16: 0.80486 | BB16: 0.81406 | BC16: 0.82303 | BD16: 0.83178 | BF16: 0.26024 | BG16: 0.26708 | BH16: 0.2741 | BI16: 0.2813 | BJ16: 0.2887 | BK16: 0.29627 | BL16: 0.30404 | BM16: 0.31199 | BN16: 0.32012 | BO16: 0.3284 | BP16: 0.33684 | BQ16: 0.34543 | BR16: 0.35416 | BS16: 0.36303 | BT16: 0.37205 | BU16: 0.38123 | BV16: 0.39057 | BW16: 0.40008 | BX16: 0.40977 | BY16: 0.41963 | BZ16: 0.42967 | CA16: 0.43987 | CB16: 0.45025 | CC16: 0.46079 | CD16: 0.47149 | CE16: 0.48233 | CF16: 0.49333 | CG16: 0.50449 | CH16: 0.51585 | CI16: 0.52743 | CJ16: 0.53924 | CK16: 0.55129 | CL16: 0.56355 | CM16: 0.57599 | CN16: 0.58854 | CO16: 0.60116 | CP16: 0.61382 | CQ16: 0.62653 | CR16: 0.6393 | CS16: 0.65217 | CT16: 0.66517 | CU16: 0.6783 | CV16: 0.6915 | CW16: 0.70471 | CX16: 0.71782 | CY16: 0.73074 | CZ16: 0.74341 | DA16: 0.75581 | DB16: 0.76794 | DC16: 0.77981 | DD16: 0.79146 | DE16: 0.80287
D17: 17 | E17: 0.30216 | F17: 0.31002 | G17: 0.3181 | H17: 0.32638 | I17: 0.33487 | J17: 0.34357 | K17: 0.35248 | L17: 0.36157 | M17: 0.37085 | N17: 0.38031 | O17: 0.38995 | P17: 0.39976 | Q17: 0.40974 | R17: 0.41988 | S17: 0.43018 | T17: 0.44064 | U17: 0.45126 | V17: 0.46204 | W17: 0.47299 | X17: 0.4841 | Y17: 0.49536 | Z17: 0.50677 | AA17: 0.5183 | AB17: 0.52993 | AC17: 0.54165 | AD17: 0.55343 | AE17: 0.56526 | AF17: 0.57716 | AG17: 0.58912 | AH17: 0.60114 | AI17: 0.6132 | AJ17: 0.62531 | AK17: 0.63741 | AL17: 0.64948 | AM17: 0.66148 | AN17: 0.6734 | AO17: 0.68522 | AP17: 0.69695 | AQ17: 0.7086 | AR17: 0.72016 | AS17: 0.73162 | AT17: 0.74293 | AU17: 0.75405 | AV17: 0.76489 | AW17: 0.77541 | AX17: 0.78557 | AY17: 0.79538 | AZ17: 0.80486 | BA17: 0.81406 | BB17: 0.82303 | BC17: 0.83178 | BD17: 0.84029 | BF17: 0.26708 | BG17: 0.2741 | BH17: 0.2813 | BI17: 0.2887 | BJ17: 0.29627 | BK17: 0.30404 | BL17: 0.31199 | BM17: 0.32012 | BN17: 0.3284 | BO17: 0.33684 | BP17: 0.34543 | BQ17: 0.35416 | BR17: 0.36303 | BS17: 0.37205 | BT17: 0.38123 | BU17: 0.39057 | BV17: 0.40008 | BW17: 0.40977 | BX17: 0.41963 | BY17: 0.42967 | BZ17: 0.43987 | CA17: 0.45025 | CB17: 0.46079 | CC17: 0.47149 | CD17: 0.48233 | CE17: 0.49333 | CF17: 0.50449 | CG17: 0.51585 | CH17: 0.52743 | CI17: 0.53924 | CJ17: 0.55129 | CK17: 0.56355 | CL17: 0.57599 | CM17: 0.58854 | CN17: 0.60116 | CO17: 0.61382 | CP17: 0.62653 | CQ17: 0.6393 | CR17: 0.65217 | CS17: 0.66517 | CT17: 0.6783 | CU17: 0.6915 | CV17: 0.70471 | CW17: 0.71782 | CX17: 0.73074 | CY17: 0.74341 | CZ17: 0.75581 | DA17: 0.76794 | DB17: 0.77981 | DC17: 0.79146 | DD17: 0.80287 | DE17: 0.814
D18: 18 | E18: 0.31002 | F18: 0.3181 | G18: 0.32638 | H18: 0.33487 | I18: 0.34357 | J18: 0.35248 | K18: 0.36157 | L18: 0.37085 | M18: 0.38031 | N18: 0.38995 | O18: 0.39976 | P18: 0.40974 | Q18: 0.41988 | R18: 0.43018 | S18: 0.44064 | T18: 0.45126 | U18: 0.46204 | V18: 0.47299 | W18: 0.4841 | X18: 0.49536 | Y18: 0.50677 | Z18: 0.5183 | AA18: 0.52993 | AB18: 0.54165 | AC18: 0.55343 | AD18: 0.56526 | AE18: 0.57716 | AF18: 0.58912 | AG18: 0.60114 | AH18: 0.6132 | AI18: 0.62531 | AJ18: 0.63741 | AK18: 0.64948 | AL18: 0.66148 | AM18: 0.6734 | AN18: 0.68522 | AO18: 0.69695 | AP18: 0.7086 | AQ18: 0.72016 | AR18: 0.73162 | AS18: 0.74293 | AT18: 0.75405 | AU18: 0.76489 | AV18: 0.77541 | AW18: 0.78557 | AX18: 0.79538 | AY18: 0.80486 | AZ18: 0.81406 | BA18: 0.82303 | BB18: 0.83178 | BC18: 0.84029 | BD18: 0.84852 | BF18: 0.2741 | BG18: 0.2813 | BH18: 0.2887 | BI18: 0.29627 | BJ18: 0.30404 | BK18: 0.31199 | BL18: 0.32012 | BM18: 0.3284 | BN18: 0.33684 | BO18: 0.34543 | BP18: 0.35416 | BQ18: 0.36303 | BR18: 0.37205 | BS18: 0.38123 | BT18: 0.39057 | BU18: 0.40008 | BV18: 0.40977 | BW18: 0.41963 | BX18: 0.42967 | BY18: 0.43987 | BZ18: 0.45025 | CA18: 0.46079 | CB18: 0.47149 | CC18: 0.48233 | CD18: 0.49333 | CE18: 0.50449 | CF18: 0.51585 | CG18: 0.52743 | CH18: 0.53924 | CI18: 0.55129 | CJ18: 0.56355 | CK18: 0.57599 | CL18: 0.58854 | CM18: 0.60116 | CN18: 0.61382 | CO18: 0.62653 | CP18: 0.6393 | CQ18: 0.65217 | CR18: 0.66517 | CS18: 0.6783 | CT18: 0.6915 | CU18: 0.70471 | CV18: 0.71782 | CW18: 0.73074 | CX18: 0.74341 | CY18: 0.75581 | CZ18: 0.76794 | DA18: 0.77981 | DB18: 0.79146 | DC18: 0.80287 | DD18: 0.814 | DE18: 0.82478
D19: 19 | E19: 0.3181 | F19: 0.32638 | G19: 0.33487 | H19: 0.34357 | I19: 0.35248 | J19: 0.36157 | K19: 0.37085 | L19: 0.38031 | M19: 0.38995 | N19: 0.39976 | O19: 0.40974 | P19: 0.41988 | Q19: 0.43018 | R19: 0.44064 | S19: 0.45126 | T19: 0.46204 | U19: 0.47299 | V19: 0.4841 | W19: 0.49536 | X19: 0.50677 | Y19: 0.5183 | Z19: 0.52993 | AA19: 0.54165 | AB19: 0.55343 | AC19: 0.56526 | AD19: 0.57716 | AE19: 0.58912 | AF19: 0.60114 | AG19: 0.6132 | AH19: 0.62531 | AI19: 0.63741 | AJ19: 0.64948 | AK19: 0.66148 | AL19: 0.6734 | AM19: 0.68522 | AN19: 0.69695 | AO19: 0.7086 | AP19: 0.72016 | AQ19: 0.73162 | AR19: 0.74293 | AS19: 0.75405 | AT19: 0.76489 | AU19: 0.77541 | AV19: 0.78557 | AW19: 0.79538 | AX19: 0.80486 | AY19: 0.81406 | AZ19: 0.82303 | BA19: 0.83178 | BB19: 0.84029 | BC19: 0.84852 | BD19: 0.8564 | BF19: 0.2813 | BG19: 0.2887 | BH19: 0.29627 | BI19: 0.30404 | BJ19: 0.31199 | BK19: 0.32012 | BL19: 0.3284 | BM19: 0.33684 | BN19: 0.34543 | BO19: 0.35416 | BP19: 0.36303 | BQ19: 0.37205 | BR19: 0.38123 | BS19: 0.39057 | BT19: 0.40008 | BU19: 0.40977 | BV19: 0.41963 | BW19: 0.42967 | BX19: 0.43987 | BY19: 0.45025 | BZ19: 0.46079 | CA19: 0.47149 | CB19: 0.48233 | CC19: 0.49333 | CD19: 0.50449 | CE19: 0.51585 | CF19: 0.52743 | CG19: 0.53924 | CH19: 0.55129 | CI19: 0.56355 | CJ19: 0.57599 | CK19: 0.58854 | CL19: 0.60116 | CM19: 0.61382 | CN19: 0.62653 | CO19: 0.6393 | CP19: 0.65217 | CQ19: 0.66517 | CR19: 0.6783 | CS19: 0.6915 | CT19: 0.70471 | CU19: 0.71782 | CV19: 0.73074 | CW19: 0.74341 | CX19: 0.75581 | CY19: 0.76794 | CZ19: 0.77981 | DA19: 0.79146 | DB19: 0.80287 | DC19: 0.814 | DD19: 0.82478 | DE19: 0.83514
D20: 20 | E20: 0.32638 | F20: 0.33487 | G20: 0.34357 | H20: 0.35248 | I20: 0.36157 | J20: 0.37085 | K20: 0.38031 | L20: 0.38995 | M20: 0.39976 | N20: 0.40974 | O20: 0.41988 | P20: 0.43018 | Q20: 0.44064 | R20: 0.45126 | S20: 0.46204 | T20: 0.47299 | U20: 0.4841 | V20: 0.49536 | W20: 0.50677 | X20: 0.5183 | Y20: 0.52993 | Z20: 0.54165 | AA20: 0.55343 | AB20: 0.56526 | AC20: 0.57716 | AD20: 0.58912 | AE20: 0.60114 | AF20: 0.6132 | AG20: 0.62531 | AH20: 0.63741 | AI20: 0.64948 | AJ20: 0.66148 | AK20: 0.6734 | AL20: 0.68522 | AM20: 0.69695 | AN20: 0.7086 | AO20: 0.72016 | AP20: 0.73162 | AQ20: 0.74293 | AR20: 0.75405 | AS20: 0.76489 | AT20: 0.77541 | AU20: 0.78557 | AV20: 0.79538 | AW20: 0.80486 | AX20: 0.81406 | AY20: 0.82303 | AZ20: 0.83178 | BA20: 0.84029 | BB20: 0.84852 | BC20: 0.8564 | BD20: 0.86387 | BF20: 0.2887 | BG20: 0.29627 | BH20: 0.30404 | BI20: 0.31199 | BJ20: 0.32012 | BK20: 0.3284 | BL20: 0.33684 | BM20: 0.34543 | BN20: 0.35416 | BO20: 0.36303 | BP20: 0.37205 | BQ20: 0.38123 | BR20: 0.39057 | BS20: 0.40008 | BT20: 0.40977 | BU20: 0.41963 | BV20: 0.42967 | BW20: 0.43987 | BX20: 0.45025 | BY20: 0.46079 | BZ20: 0.47149 | CA20: 0.48233 | CB20: 0.49333 | CC20: 0.50449 | CD20: 0.51585 | CE20: 0.52743 | CF20: 0.53924 | CG20: 0.55129 | CH20: 0.56355 | CI20: 0.57599 | CJ20: 0.58854 | CK20: 0.60116 | CL20: 0.61382 | CM20: 0.62653 | CN20: 0.6393 | CO20: 0.65217 | CP20: 0.66517 | CQ20: 0.6783 | CR20: 0.6915 | CS20: 0.70471 | CT20: 0.71782 | CU20: 0.73074 | CV20: 0.74341 | CW20: 0.75581 | CX20: 0.76794 | CY20: 0.77981 | CZ20: 0.79146 | DA20: 0.80287 | DB20: 0.814 | DC20: 0.82478 | DD20: 0.83514 | DE20: 0.84503
D21: 21 | E21: 0.33487 | F21: 0.34357 | G21: 0.35248 | H21: 0.36157 | I21: 0.37085 | J21: 0.38031 | K21: 0.38995 | L21: 0.39976 | M21: 0.40974 | N21: 0.41988 | O21: 0.43018 | P21: 0.44064 | Q21: 0.45126 | R21: 0.46204 | S21: 0.47299 | T21: 0.4841 | U21: 0.49536 | V21: 0.50677 | W21: 0.5183 | X21: 0.52993 | Y21: 0.54165 | Z21: 0.55343 | AA21: 0.56526 | AB21: 0.57716 | AC21: 0.58912 | AD21: 0.60114 | AE21: 0.6132 | AF21: 0.62531 | AG21: 0.63741 | AH21: 0.64948 | AI21: 0.66148 | AJ21: 0.6734 | AK21: 0.68522 | AL21: 0.69695 | AM21: 0.7086 | AN21: 0.72016 | AO21: 0.73162 | AP21: 0.74293 | AQ21: 0.75405 | AR21: 0.76489 | AS21: 0.77541 | AT21: 0.78557 | AU21: 0.79538 | AV21: 0.80486 | AW21: 0.81406 | AX21: 0.82303 | AY21: 0.83178 | AZ21: 0.84029 | BA21: 0.84852 | BB21: 0.8564 | BC21: 0.86387 | BD21: 0.87092 | BF21: 0.29627 | BG21: 0.30404 | BH21: 0.31199 | BI21: 0.32012 | BJ21: 0.3284 | BK21: 0.33684 | BL21: 0.34543 | BM21: 0.35416 | BN21: 0.36303 | BO21: 0.37205 | BP21: 0.38123 | BQ21: 0.39057 | BR21: 0.40008 | BS21: 0.40977 | BT21: 0.41963 | BU21: 0.42967 | BV21: 0.43987 | BW21: 0.45025 | BX21: 0.46079 | BY21: 0.47149 | BZ21: 0.48233 | CA21: 0.49333 | CB21: 0.50449 | CC21: 0.51585 | CD21: 0.52743 | CE21: 0.53924 | CF21: 0.55129 | CG21: 0.56355 | CH21: 0.57599 | CI21: 0.58854 | CJ21: 0.60116 | CK21: 0.61382 | CL21: 0.62653 | CM21: 0.6393 | CN21: 0.65217 | CO21: 0.66517 | CP21: 0.6783 | CQ21: 0.6915 | CR21: 0.70471 | CS21: 0.71782 | CT21: 0.73074 | CU21: 0.74341 | CV21: 0.75581 | CW21: 0.76794 | CX21: 0.77981 | CY21: 0.79146 | CZ21: 0.80287 | DA21: 0.814 | DB21: 0.82478 | DC21: 0.83514 | DD21: 0.84503 | DE21: 0.85442
D22: 22 | E22: 0.34357 | F22: 0.35248 | G22: 0.36157 | H22: 0.37085 | I22: 0.38031 | J22: 0.38995 | K22: 0.39976 | L22: 0.40974 | M22: 0.41988 | N22: 0.43018 | O22: 0.44064 | P22: 0.45126 | Q22: 0.46204 | R22: 0.47299 | S22: 0.4841 | T22: 0.49536 | U22: 0.50677 | V22: 0.5183 | W22: 0.52993 | X22: 0.54165 | Y22: 0.55343 | Z22: 0.56526 | AA22: 0.57716 | AB22: 0.58912 | AC22: 0.60114 | AD22: 0.6132 | AE22: 0.62531 | AF22: 0.63741 | AG22: 0.64948 | AH22: 0.66148 | AI22: 0.6734 | AJ22: 0.68522 | AK22: 0.69695 | AL22: 0.7086 | AM22: 0.72016 | AN22: 0.73162 | AO22: 0.74293 | AP22: 0.75405 | AQ22: 0.76489 | AR22: 0.77541 | AS22: 0.78557 | AT22: 0.79538 | AU22: 0.80486 | AV22: 0.81406 | AW22: 0.82303 | AX22: 0.83178 | AY22: 0.84029 | AZ22: 0.84852 | BA22: 0.8564 | BB22: 0.86387 | BC22: 0.87092 | BD22: 0.87759 | BF22: 0.30404 | BG22: 0.31199 | BH22: 0.32012 | BI22: 0.3284 | BJ22: 0.33684 | BK22: 0.34543 | BL22: 0.35416 | BM22: 0.36303 | BN22: 0.37205 | BO22: 0.38123 | BP22: 0.39057 | BQ22: 0.40008 | BR22: 0.40977 | BS22: 0.41963 | BT22: 0.42967 | BU22: 0.43987 | BV22: 0.45025 | BW22: 0.46079 | BX22: 0.47149 | BY22: 0.48233 | BZ22: 0.49333 | CA22: 0.50449 | CB22: 0.51585 | CC22: 0.52743 | CD22: 0.53924 | CE22: 0.55129 | CF22: 0.56355 | CG22: 0.57599 | CH22: 0.58854 | CI22: 0.60116 | CJ22: 0.61382 | CK22: 0.62653 | CL22: 0.6393 | CM22: 0.65217 | CN22: 0.66517 | CO22: 0.6783 | CP22: 0.6915 | CQ22: 0.70471 | CR22: 0.71782 | CS22: 0.73074 | CT22: 0.74341 | CU22: 0.75581 | CV22: 0.76794 | CW22: 0.77981 | CX22: 0.79146 | CY22: 0.80287 | CZ22: 0.814 | DA22: 0.82478 | DB22: 0.83514 | DC22: 0.84503 | DD22: 0.85442 | DE22: 0.86334
D23: 23 | E23: 0.35248 | F23: 0.36157 | G23: 0.37085 | H23: 0.38031 | I23: 0.38995 | J23: 0.39976 | K23: 0.40974 | L23: 0.41988 | M23: 0.43018 | N23: 0.44064 | O23: 0.45126 | P23: 0.46204 | Q23: 0.47299 | R23: 0.4841 | S23: 0.49536 | T23: 0.50677 | U23: 0.5183 | V23: 0.52993 | W23: 0.54165 | X23: 0.55343 | Y23: 0.56526 | Z23: 0.57716 | AA23: 0.58912 | AB23: 0.60114 | AC23: 0.6132 | AD23: 0.62531 | AE23: 0.63741 | AF23: 0.64948 | AG23: 0.66148 | AH23: 0.6734 | AI23: 0.68522 | AJ23: 0.69695 | AK23: 0.7086 | AL23: 0.72016 | AM23: 0.73162 | AN23: 0.74293 | AO23: 0.75405 | AP23: 0.76489 | AQ23: 0.77541 | AR23: 0.78557 | AS23: 0.79538 | AT23: 0.80486 | AU23: 0.81406 | AV23: 0.82303 | AW23: 0.83178 | AX23: 0.84029 | AY23: 0.84852 | AZ23: 0.8564 | BA23: 0.86387 | BB23: 0.87092 | BC23: 0.87759 | BD23: 0.88393 | BF23: 0.31199 | BG23: 0.32012 | BH23: 0.3284 | BI23: 0.33684 | BJ23: 0.34543 | BK23: 0.35416 | BL23: 0.36303 | BM23: 0.37205 | BN23: 0.38123 | BO23: 0.39057 | BP23: 0.40008 | BQ23: 0.40977 | BR23: 0.41963 | BS23: 0.42967 | BT23: 0.43987 | BU23: 0.45025 | BV23: 0.46079 | BW23: 0.47149 | BX23: 0.48233 | BY23: 0.49333 | BZ23: 0.50449 | CA23: 0.51585 | CB23: 0.52743 | CC23: 0.53924 | CD23: 0.55129 | CE23: 0.56355 | CF23: 0.57599 | CG23: 0.58854 | CH23: 0.60116 | CI23: 0.61382 | CJ23: 0.62653 | CK23: 0.6393 | CL23: 0.65217 | CM23: 0.66517 | CN23: 0.6783 | CO23: 0.6915 | CP23: 0.70471 | CQ23: 0.71782 | CR23: 0.73074 | CS23: 0.74341 | CT23: 0.75581 | CU23: 0.76794 | CV23: 0.77981 | CW23: 0.79146 | CX23: 0.80287 | CY23: 0.814 | CZ23: 0.82478 | DA23: 0.83514 | DB23: 0.84503 | DC23: 0.85442 | DD23: 0.86334 | DE23: 0.87183
... D36: 36 | E36: 0.4841 | F36: 0.49536 | G36: 0.50677 | H36: 0.5183 | I36: 0.52993 | J36: 0.54165 | K36: 0.55343 | L36: 0.56526 | M36: 0.57716 | N36: 0.58912 | O36: 0.60114 | P36: 0.6132 | Q36: 0.62531 | R36: 0.63741 | S36: 0.64948 | T36: 0.66148 | U36: 0.6734 | V36: 0.68522 | W36: 0.69695 | X36: 0.7086 | Y36: 0.72016 | Z36: 0.73162 | AA36: 0.74293 | AB36: 0.75405 | AC36: 0.76489 | AD36: 0.77541 | AE36: 0.78557 | AF36: 0.79538 | AG36: 0.80486 | AH36: 0.81406 | AI36: 0.82303 | AJ36: 0.83178 | AK36: 0.84029 | AL36: 0.84852 | AM36: 0.8564 | AN36: 0.86387 | AO36: 0.87092 | AP36: 0.87759 | AQ36: 0.88393 | AR36: 0.89002 | AS36: 0.89596 | AT36: 0.90188 | AU36: 0.90789 | AV36: 0.91418 | AW36: 0.92093 | AX36: 0.92834 | AY36: 0.93652 | AZ36: 0.9454 | BA36: 0.95468 | BB36: 0.96367 | BC36: 0.97087 | BD36: 1 | BF36: 0.42967 | BG36: 0.43987 | BH36: 0.45025 | BI36: 0.46079 | BJ36: 0.47149 | BK36: 0.48233 | BL36: 0.49333 | BM36: 0.50449 | BN36: 0.51585 | BO36: 0.52743 | BP36: 0.53924 | BQ36: 0.55129 | BR36: 0.56355 | BS36: 0.57599 | BT36: 0.58854 | BU36: 0.60116 | BV36: 0.61382 | BW36: 0.62653 | BX36: 0.6393 | BY36: 0.65217 | BZ36: 0.66517 | CA36: 0.6783 | CB36: 0.6915 | CC36: 0.70471 | CD36: 0.71782 | CE36: 0.73074 | CF36: 0.74341 | CG36: 0.75581 | CH36: 0.76794 | CI36: 0.77981 | CJ36: 0.79146 | CK36: 0.80287 | CL36: 0.814 | CM36: 0.82478 | CN36: 0.83514 | CO36: 0.84503 | CP36: 0.85442 | CQ36: 0.86334 | CR36: 0.87183 | CS36: 0.87996 | CT36: 0.8878 | CU36: 0.89546 | CV36: 0.90304 | CW36: 0.91069 | CX36: 0.91857 | CY36: 0.92687 | CZ36: 0.93569 | DA36: 0.945 | DB36: 0.95453 | DC36: 0.96363 | DD36: 0.97087 | DE36: 1
D37: 37 | E37: 0.49536 | F37: 0.50677 | G37: 0.5183 | H37: 0.52993 | I37: 0.54165 | J37: 0.55343 | K37: 0.56526 | L37: 0.57716 | M37: 0.58912 | N37: 0.60114 | O37: 0.6132 | P37: 0.62531 | Q37: 0.63741 | R37: 0.64948 | S37: 0.66148 | T37: 0.6734 | U37: 0.68522 | V37: 0.69695 | W37: 0.7086 | X37: 0.72016 | Y37: 0.73162 | Z37: 0.74293 | AA37: 0.75405 | AB37: 0.76489 | AC37: 0.77541 | AD37: 0.78557 | AE37: 0.79538 | AF37: 0.80486 | AG37: 0.81406 | AH37: 0.82303 | AI37: 0.83178 | AJ37: 0.84029 | AK37: 0.84852 | AL37: 0.8564 | AM37: 0.86387 | AN37: 0.87092 | AO37: 0.87759 | AP37: 0.88393 | AQ37: 0.89002 | AR37: 0.89596 | AS37: 0.90188 | AT37: 0.90789 | AU37: 0.91418 | AV37: 0.92093 | AW37: 0.92834 | AX37: 0.93652 | AY37: 0.9454 | AZ37: 0.95468 | BA37: 0.96367 | BB37: 0.97087 | BC37: 1 | BF37: 0.43987 | BG37: 0.45025 | BH37: 0.46079 | BI37: 0.47149 | BJ37: 0.48233 | BK37: 0.49333 | BL37: 0.50449 | BM37: 0.51585 | BN37: 0.52743 | BO37: 0.53924 | BP37: 0.55129 | BQ37: 0.56355 | BR37: 0.57599 | BS37: 0.58854 | BT37: 0.60116 | BU37: 0.61382 | BV37: 0.62653 | BW37: 0.6393 | BX37: 0.65217 | BY37: 0.66517 | BZ37: 0.6783 | CA37: 0.6915 | CB37: 0.70471 | CC37: 0.71782 | CD37: 0.73074 | CE37: 0.74341 | CF37: 0.75581 | CG37: 0.76794 | CH37: 0.77981 | CI37: 0.79146 | CJ37: 0.80287 | CK37: 0.814 | CL37: 0.82478 | CM37: 0.83514 | CN37: 0.84503 | CO37: 0.85442 | CP37: 0.86334 | CQ37: 0.87183 | CR37: 0.87996 | CS37: 0.8878 | CT37: 0.89546 | CU37: 0.90304 | CV37: 0.91069 | CW37: 0.91857 | CX37: 0.92687 | CY37: 0.93569 | CZ37: 0.945 | DA37: 0.95453 | DB37: 0.96363 | DC37: 0.97087 | DD37: 1
D38: 38 | E38: 0.50677 | F38: 0.5183 | G38: 0.52993 | H38: 0.54165 | I38: 0.55343 | J38: 0.56526 | K38: 0.57716 | L38: 0.58912 | M38: 0.60114 | N38: 0.6132 | O38: 0.62531 | P38: 0.63741 | Q38: 0.64948 | R38: 0.66148 | S38: 0.6734 | T38: 0.68522 | U38: 0.69695 | V38: 0.7086 | W38: 0.72016 | X38: 0.73162 | Y38: 0.74293 | Z38: 0.75405 | AA38: 0.76489 | AB38: 0.77541 | AC38: 0.78557 | AD38: 0.79538 | AE38: 0.80486 | AF38: 0.81406 | AG38: 0.82303 | AH38: 0.83178 | AI38: 0.84029 | AJ38: 0.84852 | AK38: 0.8564 | AL38: 0.86387 | AM38: 0.87092 | AN38: 0.87759 | AO38: 0.88393 | AP38: 0.89002 | AQ38: 0.89596 | AR38: 0.90188 | AS38: 0.90789 | AT38: 0.91418 | AU38: 0.92093 | AV38: 0.92834 | AW38: 0.93652 | AX38: 0.9454 | AY38: 0.95468 | AZ38: 0.96367 | BA38: 0.97087 | BB38: 1 | BF38: 0.45025 | BG38: 0.46079 | BH38: 0.47149 | BI38: 0.48233 | BJ38: 0.49333 | BK38: 0.50449 | BL38: 0.51585 | BM38: 0.52743 | BN38: 0.53924 | BO38: 0.55129 | BP38: 0.56355 | BQ38: 0.57599 | BR38: 0.58854 | BS38: 0.60116 | BT38: 0.61382 | BU38: 0.62653 | BV38: 0.6393 | BW38: 0.65217 | BX38: 0.66517 | BY38: 0.6783 | BZ38: 0.6915 | CA38: 0.70471 | CB38: 0.71782 | CC38: 0.73074 | CD38: 0.74341 | CE38: 0.75581 | CF38: 0.76794 | CG38: 0.77981 | CH38: 0.79146 | CI38: 0.80287 | CJ38: 0.814 | CK38: 0.82478 | CL38: 0.83514 | CM38: 0.84503 | CN38: 0.85442 | CO38: 0.86334 | CP38: 0.87183 | CQ38: 0.87996 | CR38: 0.8878 | CS38: 0.89546 | CT38: 0.90304 | CU38: 0.91069 | CV38: 0.91857 | CW38: 0.92687 | CX38: 0.93569 | CY38: 0.945 | CZ38: 0.95453 | DA38: 0.96363 | DB38: 0.97087 | DC38: 1
D39: 39 | E39: 0.5183 | F39: 0.52993 | G39: 0.54165 | H39: 0.55343 | I39: 0.56526 | J39: 0.57716 | K39: 0.58912 | L39: 0.60114 | M39: 0.6132 | N39: 0.62531 | O39: 0.63741 | P39: 0.64948 | Q39: 0.66148 | R39: 0.6734 | S39: 0.68522 | T39: 0.69695 | U39: 0.7086 | V39: 0.72016 | W39: 0.73162 | X39: 0.74293 | Y39: 0.75405 | Z39: 0.76489 | AA39: 0.77541 | AB39: 0.78557 | AC39: 0.79538 | AD39: 0.80486 | AE39: 0.81406 | AF39: 0.82303 | AG39: 0.83178 | AH39: 0.84029 | AI39: 0.84852 | AJ39: 0.8564 | AK39: 0.86387 | AL39: 0.87092 | AM39: 0.87759 | AN39: 0.88393 | AO39: 0.89002 | AP39: 0.89596 | AQ39: 0.90188 | AR39: 0.90789 | AS39: 0.91418 | AT39: 0.92093 | AU39: 0.92834 | AV39: 0.93652 | AW39: 0.9454 | AX39: 0.95468 | AY39: 0.96367 | AZ39: 0.97087 | BA39: 1 | BF39: 0.46079 | BG39: 0.47149 | BH39: 0.48233 | BI39: 0.49333 | BJ39: 0.50449 | BK39: 0.51585 | BL39: 0.52743 | BM39: 0.53924 | BN39: 0.55129 | BO39: 0.56355 | BP39: 0.57599 | BQ39: 0.58854 | BR39: 0.60116 | BS39: 0.61382 | BT39: 0.62653 | BU39: 0.6393 | BV39: 0.65217 | BW39: 0.66517 | BX39: 0.6783 | BY39: 0.6915 | BZ39: 0.70471 | CA39: 0.71782 | CB39: 0.73074 | CC39: 0.74341 | CD39: 0.75581 | CE39: 0.76794 | CF39: 0.77981 | CG39: 0.79146 | CH39: 0.80287 | CI39: 0.814 | CJ39: 0.82478 | CK39: 0.83514 | CL39: 0.84503 | CM39: 0.85442 | CN39: 0.86334 | CO39: 0.87183 | CP39: 0.87996 | CQ39: 0.8878 | CR39: 0.89546 | CS39: 0.90304 | CT39: 0.91069 | CU39: 0.91857 | CV39: 0.92687 | CW39: 0.93569 | CX39: 0.945 | CY39: 0.95453 | CZ39: 0.96363 | DA39: 0.97087 | DB39: 1
D40: 40 | E40: 0.52993 | F40: 0.54165 | G40: 0.55343 | H40: 0.56526 | I40: 0.57716 | J40: 0.58912 | K40: 0.60114 | L40: 0.6132 | M40: 0.62531 | N40: 0.63741 | O40: 0.64948 | P40: 0.66148 | Q40: 0.6734 | R40: 0.68522 | S40: 0.69695 | T40: 0.7086 | U40: 0.72016 | V40: 0.73162 | W40: 0.74293 | X40: 0.75405 | Y40: 0.76489 | Z40: 0.77541 | AA40: 0.78557 | AB40: 0.79538 | AC40: 0.80486 | AD40: 0.81406 | AE40: 0.82303 | AF40: 0.83178 | AG40: 0.84029 | AH40: 0.84852 | AI40: 0.8564 | AJ40: 0.86387 | AK40: 0.87092 | AL40: 0.87759 | AM40: 0.88393 | AN40: 0.89002 | AO40: 0.89596 | AP40: 0.90188 | AQ40: 0.90789 | AR40: 0.91418 | AS40: 0.92093 | AT40: 0.92834 | AU40: 0.93652 | AV40: 0.9454 | AW40: 0.95468 | AX40: 0.96367 | AY40: 0.97087 | AZ40: 1 | BF40: 0.47149 | BG40: 0.48233 | BH40: 0.49333 | BI40: 0.50449 | BJ40: 0.51585 | BK40: 0.52743 | BL40: 0.53924 | BM40: 0.55129 | BN40: 0.56355 | BO40: 0.57599 | BP40: 0.58854 | BQ40: 0.60116 | BR40: 0.61382 | BS40: 0.62653 | BT40: 0.6393 | BU40: 0.65217 | BV40: 0.66517 | BW40: 0.6783 | BX40: 0.6915 | BY40: 0.70471 | BZ40: 0.71782 | CA40: 0.73074 | CB40: 0.74341 | CC40: 0.75581 | CD40: 0.76794 | CE40: 0.77981 | CF40: 0.79146 | CG40: 0.80287 | CH40: 0.814 | CI40: 0.82478 | CJ40: 0.83514 | CK40: 0.84503 | CL40: 0.85442 | CM40: 0.86334 | CN40: 0.87183 | CO40: 0.87996 | CP40: 0.8878 | CQ40: 0.89546 | CR40: 0.90304 | CS40: 0.91069 | CT40: 0.91857 | CU40: 0.92687 | CV40: 0.93569 | CW40: 0.945 | CX40: 0.95453 | CY40: 0.96363 | CZ40: 0.97087 | DA40: 1
D41: 41 | E41: 0.54165 | F41: 0.55343 | G41: 0.56526 | H41: 0.57716 | I41: 0.58912 | J41: 0.60114 | K41: 0.6132 | L41: 0.62531 | M41: 0.63741 | N41: 0.64948 | O41: 0.66148 | P41: 0.6734 | Q41: 0.68522 | R41: 0.69695 | S41: 0.7086 | T41: 0.72016 | U41: 0.73162 | V41: 0.74293 | W41: 0.75405 | X41: 0.76489 | Y41: 0.77541 | Z41: 0.78557 | AA41: 0.79538 | AB41: 0.80486 | AC41: 0.81406 | AD41: 0.82303 | AE41: 0.83178 | AF41: 0.84029 | AG41: 0.84852 | AH41: 0.8564 | AI41: 0.86387 | AJ41: 0.87092 | AK41: 0.87759 | AL41: 0.88393 | AM41: 0.89002 | AN41: 0.89596 | AO41: 0.90188 | AP41: 0.90789 | AQ41: 0.91418 | AR41: 0.92093 | AS41: 0.92834 | AT41: 0.93652 | AU41: 0.9454 | AV41: 0.95468 | AW41: 0.96367 | AX41: 0.97087 | AY41: 1 | BF41: 0.48233 | BG41: 0.49333 | BH41: 0.50449 | BI41: 0.51585 | BJ41: 0.52743 | BK41: 0.53924 | BL41: 0.55129 | BM41: 0.56355 | BN41: 0.57599 | BO41: 0.58854 | BP41: 0.60116 | BQ41: 0.61382 | BR41: 0.62653 | BS41: 0.6393 | BT41: 0.65217 | BU41: 0.66517 | BV41: 0.6783 | BW41: 0.6915 | BX41: 0.70471 | BY41: 0.71782 | BZ41: 0.73074 | CA41: 0.74341 | CB41: 0.75581 | CC41: 0.76794 | CD41: 0.77981 | CE41: 0.79146 | CF41: 0.80287 | CG41: 0.814 | CH41: 0.82478 | CI41: 0.83514 | CJ41: 0.84503 | CK41: 0.85442 | CL41: 0.86334 | CM41: 0.87183 | CN41: 0.87996 | CO41: 0.8878 | CP41: 0.89546 | CQ41: 0.90304 | CR41: 0.91069 | CS41: 0.91857 | CT41: 0.92687 | CU41: 0.93569 | CV41: 0.945 | CW41: 0.95453 | CX41: 0.96363 | CY41: 0.97087 | CZ41: 1
D42: 42 | E42: 0.55343 | F42: 0.56526 | G42: 0.57716 | H42: 0.58912 | I42: 0.60114 | J42: 0.6132 | K42: 0.62531 | L42: 0.63741 | M42: 0.64948 | N42: 0.66148 | O42: 0.6734 | P42: 0.68522 | Q42: 0.69695 | R42: 0.7086 | S42: 0.72016 | T42: 0.73162 | U42: 0.74293 | V42: 0.75405 | W42: 0.76489 | X42: 0.77541 | Y42: 0.78557 | Z42: 0.79538 | AA42: 0.80486 | AB42: 0.81406 | AC42: 0.82303 | AD42: 0.83178 | AE42: 0.84029 | AF42: 0.84852 | AG42: 0.8564 | AH42: 0.86387 | AI42: 0.87092 | AJ42: 0.87759 | AK42: 0.88393 | AL42: 0.89002 | AM42: 0.89596 | AN42: 0.90188 | AO42: 0.90789 | AP42: 0.91418 | AQ42: 0.92093 | AR42: 0.92834 | AS42: 0.93652 | AT42: 0.9454 | AU42: 0.95468 | AV42: 0.96367 | AW42: 0.97087 | AX42: 1 | BF42: 0.49333 | BG42: 0.50449 | BH42: 0.51585 | BI42: 0.52743 | BJ42: 0.53924 | BK42: 0.55129 | BL42: 0.56355 | BM42: 0.57599 | BN42: 0.58854 | BO42: 0.60116 | BP42: 0.61382 | BQ42: 0.62653 | BR42: 0.6393 | BS42: 0.65217 | BT42: 0.66517 | BU42: 0.6783 | BV42: 0.6915 | BW42: 0.70471 | BX42: 0.71782 | BY42: 0.73074 | BZ42: 0.74341 | CA42: 0.75581 | CB42: 0.76794 | CC42: 0.77981 | CD42: 0.79146 | CE42: 0.80287 | CF42: 0.814 | CG42: 0.82478 | CH42: 0.83514 | CI42: 0.84503 | CJ42: 0.85442 | CK42: 0.86334 | CL42: 0.87183 | CM42: 0.87996 | CN42: 0.8878 | CO42: 0.89546 | CP42: 0.90304 | CQ42: 0.91069 | CR42: 0.91857 | CS42: 0.92687 | CT42: 0.93569 | CU42: 0.945 | CV42: 0.95453 | CW42: 0.96363 | CX42: 0.97087 | CY42: 1
D43: 43 | E43: 0.56526 | F43: 0.57716 | G43: 0.58912 | H43: 0.60114 | I43: 0.6132 | J43: 0.62531 | K43: 0.63741 | L43: 0.64948 | M43: 0.66148 | N43: 0.6734 | O43: 0.68522 | P43: 0.69695 | Q43: 0.7086 | R43: 0.72016 | S43: 0.73162 | T43: 0.74293 | U43: 0.75405 | V43: 0.76489 | W43: 0.77541 | X43: 0.78557 | Y43: 0.79538 | Z43: 0.80486 | AA43: 0.81406 | AB43: 0.82303 | AC43: 0.83178 | AD43: 0.84029 | AE43: 0.84852 | AF43: 0.8564 | AG43: 0.86387 | AH43: 0.87092 | AI43: 0.87759 | AJ43: 0.88393 | AK43: 0.89002 | AL43: 0.89596 | AM43: 0.90188 | AN43: 0.90789 | AO43: 0.91418 | AP43: 0.92093 | AQ43: 0.92834 | AR43: 0.93652 | AS43: 0.9454 | AT43: 0.95468 | AU43: 0.96367 | AV43: 0.97087 | AW43: 1 | BF43: 0.50449 | BG43: 0.51585 | BH43: 0.52743 | BI43: 0.53924 | BJ43: 0.55129 | BK43: 0.56355 | BL43: 0.57599 | BM43: 0.58854 | BN43: 0.60116 | BO43: 0.61382 | BP43: 0.62653 | BQ43: 0.6393 | BR43: 0.65217 | BS43: 0.66517 | BT43: 0.6783 | BU43: 0.6915 | BV43: 0.70471 | BW43: 0.71782 | BX43: 0.73074 | BY43: 0.74341 | BZ43: 0.75581 | CA43: 0.76794 | CB43: 0.77981 | CC43: 0.79146 | CD43: 0.80287 | CE43: 0.814 | CF43: 0.82478 | CG43: 0.83514 | CH43: 0.84503 | CI43: 0.85442 | CJ43: 0.86334 | CK43: 0.87183 | CL43: 0.87996 | CM43: 0.8878 | CN43: 0.89546 | CO43: 0.90304 | CP43: 0.91069 | CQ43: 0.91857 | CR43: 0.92687 | CS43: 0.93569 | CT43: 0.945 | CU43: 0.95453 | CV43: 0.96363 | CW43: 0.97087 | CX43: 1
D44: 44 | E44: 0.57716 | F44: 0.58912 | G44: 0.60114 | H44: 0.6132 | I44: 0.62531 | J44: 0.63741 | K44: 0.64948 | L44: 0.66148 | M44: 0.6734 | N44: 0.68522 | O44: 0.69695 | P44: 0.7086 | Q44: 0.72016 | R44: 0.73162 | S44: 0.74293 | T44: 0.75405 | U44: 0.76489 | V44: 0.77541 | W44: 0.78557 | X44: 0.79538 | Y44: 0.80486 | Z44: 0.81406 | AA44: 0.82303 | AB44: 0.83178 | AC44: 0.84029 | AD44: 0.84852 | AE44: 0.8564 | AF44: 0.86387 | AG44: 0.87092 | AH44: 0.87759 | AI44: 0.88393 | AJ44: 0.89002 | AK44: 0.89596 | AL44: 0.90188 | AM44: 0.90789 | AN44: 0.91418 | AO44: 0.92093 | AP44: 0.92834 | AQ44: 0.93652 | AR44: 0.9454 | AS44: 0.95468 | AT44: 0.96367 | AU44: 0.97087 | AV44: 1 | BF44: 0.51585 | BG44: 0.52743 | BH44: 0.53924 | BI44: 0.55129 | BJ44: 0.56355 | BK44: 0.57599 | BL44: 0.58854 | BM44: 0.60116 | BN44: 0.61382 | BO44: 0.62653 | BP44: 0.6393 | BQ44: 0.65217 | BR44: 0.66517 | BS44: 0.6783 | BT44: 0.6915 | BU44: 0.70471 | BV44: 0.71782 | BW44: 0.73074 | BX44: 0.74341 | BY44: 0.75581 | BZ44: 0.76794 | CA44: 0.77981 | CB44: 0.79146 | CC44: 0.80287 | CD44: 0.814 | CE44: 0.82478 | CF44: 0.83514 | CG44: 0.84503 | CH44: 0.85442 | CI44: 0.86334 | CJ44: 0.87183 | CK44: 0.87996 | CL44: 0.8878 | CM44: 0.89546 | CN44: 0.90304 | CO44: 0.91069 | CP44: 0.91857 | CQ44: 0.92687 | CR44: 0.93569 | CS44: 0.945 | CT44: 0.95453 | CU44: 0.96363 | CV44: 0.97087 | CW44: 1
D45: 45 | E45: 0.58912 | F45: 0.60114 | G45: 0.6132 | H45: 0.62531 | I45: 0.63741 | J45: 0.64948 | K45: 0.66148 | L45: 0.6734 | M45: 0.68522 | N45: 0.69695 | O45: 0.7086 | P45: 0.72016 | Q45: 0.73162 | R45: 0.74293 | S45: 0.75405 | T45: 0.76489 | U45: 0.77541 | V45: 0.78557 | W45: 0.79538 | X45: 0.80486 | Y45: 0.81406 | Z45: 0.82303 | AA45: 0.83178 | AB45: 0.84029 | AC45: 0.84852 | AD45: 0.8564 | AE45: 0.86387 | AF45: 0.87092 | AG45: 0.87759 | AH45: 0.88393 | AI45: 0.89002 | AJ45: 0.89596 | AK45: 0.90188 | AL45: 0.90789 | AM45: 0.91418 | AN45: 0.92093 | AO45: 0.92834 | AP45: 0.93652 | AQ45: 0.9454 | AR45: 0.95468 | AS45: 0.96367 | AT45: 0.97087 | AU45: 1 | BF45: 0.52743 | BG45: 0.53924 | BH45: 0.55129 | BI45: 0.56355 | BJ45: 0.57599 | BK45: 0.58854 | BL45: 0.60116 | BM45: 0.61382 | BN45: 0.62653 | BO45: 0.6393 | BP45: 0.65217 | BQ45: 0.66517 | BR45: 0.6783 | BS45: 0.6915 | BT45: 0.70471 | BU45: 0.71782 | BV45: 0.73074 | BW45: 0.74341 | BX45: 0.75581 | BY45: 0.76794 | BZ45: 0.77981 | CA45: 0.79146 | CB45: 0.80287 | CC45: 0.814 | CD45: 0.82478 | CE45: 0.83514 | CF45: 0.84503 | CG45: 0.85442 | CH45: 0.86334 | CI45: 0.87183 | CJ45: 0.87996 | CK45: 0.8878 | CL45: 0.89546 | CM45: 0.90304 | CN45: 0.91069 | CO45: 0.91857 | CP45: 0.92687 | CQ45: 0.93569 | CR45: 0.945 | CS45: 0.95453 | CT45: 0.96363 | CU45: 0.97087 | CV45: 1
D46: 46 | E46: 0.60114 | F46: 0.6132 | G46: 0.62531 | H46: 0.63741 | I46: 0.64948 | J46: 0.66148 | K46: 0.6734 | L46: 0.68522 | M46: 0.69695 | N46: 0.7086 | O46: 0.72016 | P46: 0.73162 | Q46: 0.74293 | R46: 0.75405 | S46: 0.76489 | T46: 0.77541 | U46: 0.78557 | V46: 0.79538 | W46: 0.80486 | X46: 0.81406 | Y46: 0.82303 | Z46: 0.83178 | AA46: 0.84029 | AB46: 0.84852 | AC46: 0.8564 | AD46: 0.86387 | AE46: 0.87092 | AF46: 0.87759 | AG46: 0.88393 | AH46: 0.89002 | AI46: 0.89596 | AJ46: 0.90188 | AK46: 0.90789 | AL46: 0.91418 | AM46: 0.92093 | AN46: 0.92834 | AO46: 0.93652 | AP46: 0.9454 | AQ46: 0.95468 | AR46: 0.96367 | AS46: 0.97087 | AT46: 1 | BF46: 0.53924 | BG46: 0.55129 | BH46: 0.56355 | BI46: 0.57599 | BJ46: 0.58854 | BK46: 0.60116 | BL46: 0.61382 | BM46: 0.62653 | BN46: 0.6393 | BO46: 0.65217 | BP46: 0.66517 | BQ46: 0.6783 | BR46: 0.6915 | BS46: 0.70471 | BT46: 0.71782 | BU46: 0.73074 | BV46: 0.74341 | BW46: 0.75581 | BX46: 0.76794 | BY46: 0.77981 | BZ46: 0.79146 | CA46: 0.80287 | CB46: 0.814 | CC46: 0.82478 | CD46: 0.83514 | CE46: 0.84503 | CF46: 0.85442 | CG46: 0.86334 | CH46: 0.87183 | CI46: 0.87996 | CJ46: 0.8878 | CK46: 0.89546 | CL46: 0.90304 | CM46: 0.91069 | CN46: 0.91857 | CO46: 0.92687 | CP46: 0.93569 | CQ46: 0.945 | CR46: 0.95453 | CS46: 0.96363 | CT46: 0.97087 | CU46: 1
D47: 47 | E47: 0.6132 | F47: 0.62531 | G47: 0.63741 | H47: 0.64948 | I47: 0.66148 | J47: 0.6734 | K47: 0.68522 | L47: 0.69695 | M47: 0.7086 | N47: 0.72016 | O47: 0.73162 | P47: 0.74293 | Q47: 0.75405 | R47: 0.76489 | S47: 0.77541 | T47: 0.78557 | U47: 0.79538 | V47: 0.80486 | W47: 0.81406 | X47: 0.82303 | Y47: 0.83178 | Z47: 0.84029 | AA47: 0.84852 | AB47: 0.8564 | AC47: 0.86387 | AD47: 0.87092 | AE47: 0.87759 | AF47: 0.88393 | AG47: 0.89002 | AH47: 0.89596 | AI47: 0.90188 | AJ47: 0.90789 | AK47: 0.91418 | AL47: 0.92093 | AM47: 0.92834 | AN47: 0.93652 | AO47: 0.9454 | AP47: 0.95468 | AQ47: 0.96367 | AR47: 0.97087 | AS47: 1 | BF47: 0.55129 | BG47: 0.56355 | BH47: 0.57599 | BI47: 0.58854 | BJ47: 0.60116 | BK47: 0.61382 | BL47: 0.62653 | BM47: 0.6393 | BN47: 0.65217 | BO47: 0.66517 | BP47: 0.6783 | BQ47: 0.6915 | BR47: 0.70471 | BS47: 0.71782 | BT47: 0.73074 | BU47: 0.74341 | BV47: 0.75581 | BW47: 0.76794 | BX47: 0.77981 | BY47: 0.79146 | BZ47: 0.80287 | CA47: 0.814 | CB47: 0.82478 | CC47: 0.83514 | CD47: 0.84503 | CE47: 0.85442 | CF47: 0.86334 | CG47: 0.87183 | CH47: 0.87996 | CI47: 0.8878 | CJ47: 0.89546 | CK47: 0.90304 | CL47: 0.91069 | CM47: 0.91857 | CN47: 0.92687 | CO47: 0.93569 | CP47: 0.945 | CQ47: 0.95453 | CR47: 0.96363 | CS47: 0.97087 | CT47: 1
D48: 48 | E48: 0.62531 | F48: 0.63741 | G48: 0.64948 | H48: 0.66148 | I48: 0.6734 | J48: 0.68522 | K48: 0.69695 | L48: 0.7086 | M48: 0.72016 | N48: 0.73162 | O48: 0.74293 | P48: 0.75405 | Q48: 0.76489 | R48: 0.77541 | S48: 0.78557 | T48: 0.79538 | U48: 0.80486 | V48: 0.81406 | W48: 0.82303 | X48: 0.83178 | Y48: 0.84029 | Z48: 0.84852 | AA48: 0.8564 | AB48: 0.86387 | AC48: 0.87092 | AD48: 0.87759 | AE48: 0.88393 | AF48: 0.89002 | AG48: 0.89596 | AH48: 0.90188 | AI48: 0.90789 | AJ48: 0.91418 | AK48: 0.92093 | AL48: 0.92834 | AM48: 0.93652 | AN48: 0.9454 | AO48: 0.95468 | AP48: 0.96367 | AQ48: 0.97087 | AR48: 1 | BF48: 0.56355 | BG48: 0.57599 | BH48: 0.58854 | BI48: 0.60116 | BJ48: 0.61382 | BK48: 0.62653 | BL48: 0.6393 | BM48: 0.65217 | BN48: 0.66517 | BO48: 0.6783 | BP48: 0.6915 | BQ48: 0.70471 | BR48: 0.71782 | BS48: 0.73074 | BT48: 0.74341 | BU48: 0.75581 | BV48: 0.76794 | BW48: 0.77981 | BX48: 0.79146 | BY48: 0.80287 | BZ48: 0.814 | CA48: 0.82478 | CB48: 0.83514 | CC48: 0.84503 | CD48: 0.85442 | CE48: 0.86334 | CF48: 0.87183 | CG48: 0.87996 | CH48: 0.8878 | CI48: 0.89546 | CJ48: 0.90304 | CK48: 0.91069 | CL48: 0.91857 | CM48: 0.92687 | CN48: 0.93569 | CO48: 0.945 | CP48: 0.95453 | CQ48: 0.96363 | CR48: 0.97087 | CS48: 1
D49: 49 | E49: 0.63741 | F49: 0.64948 | G49: 0.66148 | H49: 0.6734 | I49: 0.68522 | J49: 0.69695 | K49: 0.7086 | L49: 0.72016 | M49: 0.73162 | N49: 0.74293 | O49: 0.75405 | P49: 0.76489 | Q49: 0.77541 | R49: 0.78557 | S49: 0.79538 | T49: 0.80486 | U49: 0.81406 | V49: 0.82303 | W49: 0.83178 | X49: 0.84029 | Y49: 0.84852 | Z49: 0.8564 | AA49: 0.86387 | AB49: 0.87092 | AC49: 0.87759 | AD49: 0.88393 | AE49: 0.89002 | AF49: 0.89596 | AG49: 0.90188 | AH49: 0.90789 | AI49: 0.91418 | AJ49: 0.92093 | AK49: 0.92834 | AL49: 0.93652 | AM49: 0.9454 | AN49: 0.95468 | AO49: 0.96367 | AP49: 0.97087 | AQ49: 1 | BF49: 0.57599 | BG49: 0.58854 | BH49: 0.60116 | BI49: 0.61382 | BJ49: 0.62653 | BK49: 0.6393 | BL49: 0.65217 | BM49: 0.66517 | BN49: 0.6783 | BO49: 0.6915 | BP49: 0.70471 | BQ49: 0.71782 | BR49: 0.73074 | BS49: 0.74341 | BT49: 0.75581 | BU49: 0.76794 | BV49: 0.77981 | BW49: 0.79146 | BX49: 0.80287 | BY49: 0.814 | BZ49: 0.82478 | CA49: 0.83514 | CB49: 0.84503 | CC49: 0.85442 | CD49: 0.86334 | CE49: 0.87183 | CF49: 0.87996 | CG49: 0.8878 | CH49: 0.89546 | CI49: 0.90304 | CJ49: 0.91069 | CK49: 0.91857 | CL49: 0.92687 | CM49: 0.93569 | CN49: 0.945 | CO49: 0.95453 | CP49: 0.96363 | CQ49: 0.97087 | CR49: 1
D50: 50 | E50: 0.64948 | F50: 0.66148 | G50: 0.6734 | H50: 0.68522 | I50: 0.69695 | J50: 0.7086 | K50: 0.72016 | L50: 0.73162 | M50: 0.74293 | N50: 0.75405 | O50: 0.76489 | P50: 0.77541 | Q50: 0.78557 | R50: 0.79538 | S50: 0.80486 | T50: 0.81406 | U50: 0.82303 | V50: 0.83178 | W50: 0.84029 | X50: 0.84852 | Y50: 0.8564 | Z50: 0.86387 | AA50: 0.87092 | AB50: 0.87759 | AC50: 0.88393 | AD50: 0.89002 | AE50: 0.89596 | AF50: 0.90188 | AG50: 0.90789 | AH50: 0.91418 | AI50: 0.92093 | AJ50: 0.92834 | AK50: 0.93652 | AL50: 0.9454 | AM50: 0.95468 | AN50: 0.96367 | AO50: 0.97087 | AP50: 1 | BF50: 0.58854 | BG50: 0.60116 | BH50: 0.61382 | BI50: 0.62653 | BJ50: 0.6393 | BK50: 0.65217 | BL50: 0.66517 | BM50: 0.6783 | BN50: 0.6915 | BO50: 0.70471 | BP50: 0.71782 | BQ50: 0.73074 | BR50: 0.74341 | BS50: 0.75581 | BT50: 0.76794 | BU50: 0.77981 | BV50: 0.79146 | BW50: 0.80287 | BX50: 0.814 | BY50: 0.82478 | BZ50: 0.83514 | CA50: 0.84503 | CB50: 0.85442 | CC50: 0.86334 | CD50: 0.87183 | CE50: 0.87996 | CF50: 0.8878 | CG50: 0.89546 | CH50: 0.90304 | CI50: 0.91069 | CJ50: 0.91857 | CK50: 0.92687 | CL50: 0.93569 | CM50: 0.945 | CN50: 0.95453 | CO50: 0.96363 | CP50: 0.97087 | CQ50: 1
D51: 51 | E51: 0.66148 | F51: 0.6734 | G51: 0.68522 | H51: 0.69695 | I51: 0.7086 | J51: 0.72016 | K51: 0.73162 | L51: 0.74293 | M51: 0.75405 | N51: 0.76489 | O51: 0.77541 | P51: 0.78557 | Q51: 0.79538 | R51: 0.80486 | S51: 0.81406 | T51: 0.82303 | U51: 0.83178 | V51: 0.84029 | W51: 0.84852 | X51: 0.8564 | Y51: 0.86387 | Z51: 0.87092 | AA51: 0.87759 | AB51: 0.88393 | AC51: 0.89002 | AD51: 0.89596 | AE51: 0.90188 | AF51: 0.90789 | AG51: 0.91418 | AH51: 0.92093 | AI51: 0.92834 | AJ51: 0.93652 | AK51: 0.9454 | AL51: 0.95468 | AM51: 0.96367 | AN51: 0.97087 | AO51: 1 | BF51: 0.60116 | BG51: 0.61382 | BH51: 0.62653 | BI51: 0.6393 | BJ51: 0.65217 | BK51: 0.66517 | BL51: 0.6783 | BM51: 0.6915 | BN51: 0.70471 | BO51: 0.71782 | BP51: 0.73074 | BQ51: 0.74341 | BR51: 0.75581 | BS51: 0.76794 | BT51: 0.77981 | BU51: 0.79146 | BV51: 0.80287 | BW51: 0.814 | BX51: 0.82478 | BY51: 0.83514 | BZ51: 0.84503 | CA51: 0.85442 | CB51: 0.86334 | CC51: 0.87183 | CD51: 0.87996 | CE51: 0.8878 | CF51: 0.89546 | CG51: 0.90304 | CH51: 0.91069 | CI51: 0.91857 | CJ51: 0.92687 | CK51: 0.93569 | CL51: 0.945 | CM51: 0.95453 | CN51: 0.96363 | CO51: 0.97087 | CP51: 1
D52: 52 | E52: 0.6734 | F52: 0.68522 | G52: 0.69695 | H52: 0.7086 | I52: 0.72016 | J52: 0.73162 | K52: 0.74293 | L52: 0.75405 | M52: 0.76489 | N52: 0.77541 | O52: 0.78557 | P52: 0.79538 | Q52: 0.80486 | R52: 0.81406 | S52: 0.82303 | T52: 0.83178 | U52: 0.84029 | V52: 0.84852 | W52: 0.8564 | X52: 0.86387 | Y52: 0.87092 | Z52: 0.87759 | AA52: 0.88393 | AB52: 0.89002 | AC52: 0.89596 | AD52: 0.90188 | AE52: 0.90789 | AF52: 0.91418 | AG52: 0.92093 | AH52: 0.92834 | AI52: 0.93652 | AJ52: 0.9454 | AK52: 0.95468 | AL52: 0.96367 | AM52: 0.97087 | AN52: 1 | BF52: 0.61382 | BG52: 0.62653 | BH52: 0.6393 | BI52: 0.65217 | BJ52: 0.66517 | BK52: 0.6783 | BL52: 0.6915 | BM52: 0.70471 | BN52: 0.71782 | BO52: 0.73074 | BP52: 0.74341 | BQ52: 0.75581 | BR52: 0.76794 | BS52: 0.77981 | BT52: 0.79146 | BU52: 0.80287 | BV52: 0.814 | BW52: 0.82478 | BX52: 0.83514 | BY52: 0.84503 | BZ52: 0.85442 | CA52: 0.86334 | CB52: 0.87183 | CC52: 0.87996 | CD52: 0.8878 | CE52: 0.89546 | CF52: 0.90304 | CG52: 0.91069 | CH52: 0.91857 | CI52: 0.92687 | CJ52: 0.93569 | CK52: 0.945 | CL52: 0.95453 | CM52: 0.96363 | CN52: 0.97087 | CO52: 1
D53: 53 | E53: 0.68522 | F53: 0.69695 | G53: 0.7086 | H53: 0.72016 | I53: 0.73162 | J53: 0.74293 | K53: 0.75405 | L53: 0.76489 | M53: 0.77541 | N53: 0.78557 | O53: 0.79538 | P53: 0.80486 | Q53: 0.81406 | R53: 0.82303 | S53: 0.83178 | T53: 0.84029 | U53: 0.84852 | V53: 0.8564 | W53: 0.86387 | X53: 0.87092 | Y53: 0.87759 | Z53: 0.88393 | AA53: 0.89002 | AB53: 0.89596 | AC53: 0.90188 | AD53: 0.90789 | AE53: 0.91418 | AF53: 0.92093 | AG53: 0.92834 | AH53: 0.93652 | AI53: 0.9454 | AJ53: 0.95468 | AK53: 0.96367 | AL53: 0.97087 | AM53: 1 | BF53: 0.62653 | BG53: 0.6393 | BH53: 0.65217 | BI53: 0.66517 | BJ53: 0.6783 | BK53: 0.6915 | BL53: 0.70471 | BM53: 0.71782 | BN53: 0.73074 | BO53: 0.74341 | BP53: 0.75581 | BQ53: 0.76794 | BR53: 0.77981 | BS53: 0.79146 | BT53: 0.80287 | BU53: 0.814 | BV53: 0.82478 | BW53: 0.83514 | BX53: 0.84503 | BY53: 0.85442 | BZ53: 0.86334 | CA53: 0.87183 | CB53: 0.87996 | CC53: 0.8878 | CD53: 0.89546 | CE53: 0.90304 | CF53: 0.91069 | CG53: 0.91857 | CH53: 0.92687 | CI53: 0.93569 | CJ53: 0.945 | CK53: 0.95453 | CL53: 0.96363 | CM53: 0.97087 | CN53: 1
D54: 54 | E54: 0.69695 | F54: 0.7086 | G54: 0.72016 | H54: 0.73162 | I54: 0.74293 | J54: 0.75405 | K54: 0.76489 | L54: 0.77541 | M54: 0.78557 | N54: 0.79538 | O54: 0.80486 | P54: 0.81406 | Q54: 0.82303 | R54: 0.83178 | S54: 0.84029 | T54: 0.84852 | U54: 0.8564 | V54: 0.86387 | W54: 0.87092 | X54: 0.87759 | Y54: 0.88393 | Z54: 0.89002 | AA54: 0.89596 | AB54: 0.90188 | AC54: 0.90789 | AD54: 0.91418 | AE54: 0.92093 | AF54: 0.92834 | AG54: 0.93652 | AH54: 0.9454 | AI54: 0.95468 | AJ54: 0.96367 | AK54: 0.97087 | AL54: 1 | BF54: 0.6393 | BG54: 0.65217 | BH54: 0.66517 | BI54: 0.6783 | BJ54: 0.6915 | BK54: 0.70471 | BL54: 0.71782 | BM54: 0.73074 | BN54: 0.74341 | BO54: 0.75581 | BP54: 0.76794 | BQ54: 0.77981 | BR54: 0.79146 | BS54: 0.80287 | BT54: 0.814 | BU54: 0.82478 | BV54: 0.83514 | BW54: 0.84503 | BX54: 0.85442 | BY54: 0.86334 | BZ54: 0.87183 | CA54: 0.87996 | CB54: 0.8878 | CC54: 0.89546 | CD54: 0.90304 | CE54: 0.91069 | CF54: 0.91857 | CG54: 0.92687 | CH54: 0.93569 | CI54: 0.945 | CJ54: 0.95453 | CK54: 0.96363 | CL54: 0.97087 | CM54: 1
D55: 55 | E55: 0.7086 | F55: 0.72016 | G55: 0.73162 | H55: 0.74293 | I55: 0.75405 | J55: 0.76489 | K55: 0.77541 | L55: 0.78557 | M55: 0.79538 | N55: 0.80486 | O55: 0.81406 | P55: 0.82303 | Q55: 0.83178 | R55: 0.84029 | S55: 0.84852 | T55: 0.8564 | U55: 0.86387 | V55: 0.87092 | W55: 0.87759 | X55: 0.88393 | Y55: 0.89002 | Z55: 0.89596 | AA55: 0.90188 | AB55: 0.90789 | AC55: 0.91418 | AD55: 0.92093 | AE55: 0.92834 | AF55: 0.93652 | AG55: 0.9454 | AH55: 0.95468 | AI55: 0.96367 | AJ55: 0.97087 | AK55: 1 | BF55: 0.65217 | BG55: 0.66517 | BH55: 0.6783 | BI55: 0.6915 | BJ55: 0.70471 | BK55: 0.71782 | BL55: 0.73074 | BM55: 0.74341 | BN55: 0.75581 | BO55: 0.76794 | BP55: 0.77981 | BQ55: 0.79146 | BR55: 0.80287 | BS55: 0.814 | BT55: 0.82478 | BU55: 0.83514 | BV55: 0.84503 | BW55: 0.85442 | BX55: 0.86334 | BY55: 0.87183 | BZ55: 0.87996 | CA55: 0.8878 | CB55: 0.89546 | CC55: 0.90304 | CD55: 0.91069 | CE55: 0.91857 | CF55: 0.92687 | CG55: 0.93569 | CH55: 0.945 | CI55: 0.95453 | CJ55: 0.96363 | CK55: 0.97087 | CL55: 1
D56: 56 | E56: 0.72016 | F56: 0.73162 | G56: 0.74293 | H56: 0.75405 | I56: 0.76489 | J56: 0.77541 | K56: 0.78557 | L56: 0.79538 | M56: 0.80486 | N56: 0.81406 | O56: 0.82303 | P56: 0.83178 | Q56: 0.84029 | R56: 0.84852 | S56: 0.8564 | T56: 0.86387 | U56: 0.87092 | V56: 0.87759 | W56: 0.88393 | X56: 0.89002 | Y56: 0.89596 | Z56: 0.90188 | AA56: 0.90789 | AB56: 0.91418 | AC56: 0.92093 | AD56: 0.92834 | AE56: 0.93652 | AF56: 0.9454 | AG56: 0.95468 | AH56: 0.96367 | AI56: 0.97087 | AJ56: 1 | BF56: 0.66517 | BG56: 0.6783 | BH56: 0.6915 | BI56: 0.70471 | BJ56: 0.71782 | BK56: 0.73074 | BL56: 0.74341 | BM56: 0.75581 | BN56: 0.76794 | BO56: 0.77981 | BP56: 0.79146 | BQ56: 0.80287 | BR56: 0.814 | BS56: 0.82478 | BT56: 0.83514 | BU56: 0.84503 | BV56: 0.85442 | BW56: 0.86334 | BX56: 0.87183 | BY56: 0.87996 | BZ56: 0.8878 | CA56: 0.89546 | CB56: 0.90304 | CC56: 0.91069 | CD56: 0.91857 | CE56: 0.92687 | CF56: 0.93569 | CG56: 0.945 | CH56: 0.95453 | CI56: 0.96363 | CJ56: 0.97087 | CK56: 1
D57: 57 | E57: 0.73162 | F57: 0.74293 | G57: 0.75405 | H57: 0.76489 | I57: 0.77541 | J57: 0.78557 | K57: 0.79538 | L57: 0.80486 | M57: 0.81406 | N57: 0.82303 | O57: 0.83178 | P57: 0.84029 | Q57: 0.84852 | R57: 0.8564 | S57: 0.86387 | T57: 0.87092 | U57: 0.87759 | V57: 0.88393 | W57: 0.89002 | X57: 0.89596 | Y57: 0.90188 | Z57: 0.90789 | AA57: 0.91418 | AB57: 0.92093 | AC57: 0.92834 | AD57: 0.93652 | AE57: 0.9454 | AF57: 0.95468 | AG57: 0.96367 | AH57: 0.97087 | AI57: 1 | BF57: 0.6783 | BG57: 0.6915 | BH57: 0.70471 | BI57: 0.71782 | BJ57: 0.73074 | BK57: 0.74341 | BL57: 0.75581 | BM57: 0.76794 | BN57: 0.77981 | BO57: 0.79146 | BP57: 0.80287 | BQ57: 0.814 | BR57: 0.82478 | BS57: 0.83514 | BT57: 0.84503 | BU57: 0.85442 | BV57: 0.86334 | BW57: 0.87183 | BX57: 0.87996 | BY57: 0.8878 | BZ57: 0.89546 | CA57: 0.90304 | CB57: 0.91069 | CC57: 0.91857 | CD57: 0.92687 | CE57: 0.93569 | CF57: 0.945 | CG57: 0.95453 | CH57: 0.96363 | CI57: 0.97087 | CJ57: 1
D58: 58 | E58: 0.74293 | F58: 0.75405 | G58: 0.76489 | H58: 0.77541 | I58: 0.78557 | J58: 0.79538 | K58: 0.80486 | L58: 0.81406 | M58: 0.82303 | N58: 0.83178 | O58: 0.84029 | P58: 0.84852 | Q58: 0.8564 | R58: 0.86387 | S58: 0.87092 | T58: 0.87759 | U58: 0.88393 | V58: 0.89002 | W58: 0.89596 | X58: 0.90188 | Y58: 0.90789 | Z58: 0.91418 | AA58: 0.92093 | AB58: 0.92834 | AC58: 0.93652 | AD58: 0.9454 | AE58: 0.95468 | AF58: 0.96367 | AG58: 0.97087 | AH58: 1 | BF58: 0.6915 | BG58: 0.70471 | BH58: 0.71782 | BI58: 0.73074 | BJ58: 0.74341 | BK58: 0.75581 | BL58: 0.76794 | BM58: 0.77981 | BN58: 0.79146 | BO58: 0.80287 | BP58: 0.814 | BQ58: 0.82478 | BR58: 0.83514 | BS58: 0.84503 | BT58: 0.85442 | BU58: 0.86334 | BV58: 0.87183 | BW58: 0.87996 | BX58: 0.8878 | BY58: 0.89546 | BZ58: 0.90304 | CA58: 0.91069 | CB58: 0.91857 | CC58: 0.92687 | CD58: 0.93569 | CE58: 0.945 | CF58: 0.95453 | CG58: 0.96363 | CH58: 0.97087 | CI58: 1
D59: 59 | E59: 0.75405 | F59: 0.76489 | G59: 0.77541 | H59: 0.78557 | I59: 0.79538 | J59: 0.80486 | K59: 0.81406 | L59: 0.82303 | M59: 0.83178 | N59: 0.84029 | O59: 0.84852 | P59: 0.8564 | Q59: 0.86387 | R59: 0.87092 | S59: 0.87759 | T59: 0.88393 | U59: 0.89002 | V59: 0.89596 | W59: 0.90188 | X59: 0.90789 | Y59: 0.91418 | Z59: 0.92093 | AA59: 0.92834 | AB59: 0.93652 | AC59: 0.9454 | AD59: 0.95468 | AE59: 0.96367 | AF59: 0.97087 | AG59: 1 | BF59: 0.70471 | BG59: 0.71782 | BH59: 0.73074 | BI59: 0.74341 | BJ59: 0.75581 | BK59: 0.76794 | BL59: 0.77981 | BM59: 0.79146 | BN59: 0.80287 | BO59: 0.814 | BP59: 0.82478 | BQ59: 0.83514 | BR59: 0.84503 | BS59: 0.85442 | BT59: 0.86334 | BU59: 0.87183 | BV59: 0.87996 | BW59: 0.8878 | BX59: 0.89546 | BY59: 0.90304 | BZ59: 0.91069 | CA59: 0.91857 | CB59: 0.92687 | CC59: 0.93569 | CD59: 0.945 | CE59: 0.95453 | CF59: 0.96363 | CG59: 0.97087 | CH59: 1
D60: 60 | E60: 0.76489 | F60: 0.77541 | G60: 0.78557 | H60: 0.79538 | I60: 0.80486 | J60: 0.81406 | K60: 0.82303 | L60: 0.83178 | M60: 0.84029 | N60: 0.84852 | O60: 0.8564 | P60: 0.86387 | Q60: 0.87092 | R60: 0.87759 | S60: 0.88393 | T60: 0.89002 | U60: 0.89596 | V60: 0.90188 | W60: 0.90789 | X60: 0.91418 | Y60: 0.92093 | Z60: 0.92834 | AA60: 0.93652 | AB60: 0.9454 | AC60: 0.95468 | AD60: 0.96367 | AE60: 0.97087 | AF60: 1 | BF60: 0.71782 | BG60: 0.73074 | BH60: 0.74341 | BI60: 0.75581 | BJ60: 0.76794 | BK60: 0.77981 | BL60: 0.79146 | BM60: 0.80287 | BN60: 0.814 | BO60: 0.82478 | BP60: 0.83514 | BQ60: 0.84503 | BR60: 0.85442 | BS60: 0.86334 | BT60: 0.87183 | BU60: 0.87996 | BV60: 0.8878 | BW60: 0.89546 | BX60: 0.90304 | BY60: 0.91069 | BZ60: 0.91857 | CA60: 0.92687 | CB60: 0.93569 | CC60: 0.945 | CD60: 0.95453 | CE60: 0.96363 | CF60: 0.97087 | CG60: 1
D61: 61 | E61: 0.77541 | F61: 0.78557 | G61: 0.79538 | H61: 0.80486 | I61: 0.81406 | J61: 0.82303 | K61: 0.83178 | L61: 0.84029 | M61: 0.84852 | N61: 0.8564 | O61: 0.86387 | P61: 0.87092 | Q61: 0.87759 | R61: 0.88393 | S61: 0.89002 | T61: 0.89596 | U61: 0.90188 | V61: 0.90789 | W61: 0.91418 | X61: 0.92093 | Y61: 0.92834 | Z61: 0.93652 | AA61: 0.9454 | AB61: 0.95468 | AC61: 0.96367 | AD61: 0.97087 | AE61: 1 | BF61: 0.73074 | BG61: 0.74341 | BH61: 0.75581 | BI61: 0.76794 | BJ61: 0.77981 | BK61: 0.79146 | BL61: 0.80287 | BM61: 0.814 | BN61: 0.82478 | BO61: 0.83514 | BP61: 0.84503 | BQ61: 0.85442 | BR61: 0.86334 | BS61: 0.87183 | BT61: 0.87996 | BU61: 0.8878 | BV61: 0.89546 | BW61: 0.90304 | BX61: 0.91069 | BY61: 0.91857 | BZ61: 0.92687 | CA61: 0.93569 | CB61: 0.945 | CC61: 0.95453 | CD61: 0.96363 | CE61: 0.97087 | CF61: 1
D62: 62 | E62: 0.78557 | F62: 0.79538 | G62: 0.80486 | H62: 0.81406 | I62: 0.82303 | J62: 0.83178 | K62: 0.84029 | L62: 0.84852 | M62: 0.8564 | N62: 0.86387 | O62: 0.87092 | P62: 0.87759 | Q62: 0.88393 | R62: 0.89002 | S62: 0.89596 | T62: 0.90188 | U62: 0.90789 | V62: 0.91418 | W62: 0.92093 | X62: 0.92834 | Y62: 0.93652 | Z62: 0.9454 | AA62: 0.95468 | AB62: 0.96367 | AC62: 0.97087 | AD62: 1 | BF62: 0.74341 | BG62: 0.75581 | BH62: 0.76794 | BI62: 0.77981 | BJ62: 0.79146 | BK62: 0.80287 | BL62: 0.814 | BM62: 0.82478 | BN62: 0.83514 | BO62: 0.84503 | BP62: 0.85442 | BQ62: 0.86334 | BR62: 0.87183 | BS62: 0.87996 | BT62: 0.8878 | BU62: 0.89546 | BV62: 0.90304 | BW62: 0.91069 | BX62: 0.91857 | BY62: 0.92687 | BZ62: 0.93569 | CA62: 0.945 | CB62: 0.95453 | CC62: 0.96363 | CD62: 0.97087 | CE62: 1
D63: 63 | E63: 0.79538 | F63: 0.80486 | G63: 0.81406 | H63: 0.82303 | I63: 0.83178 | J63: 0.84029 | K63: 0.84852 | L63: 0.8564 | M63: 0.86387 | N63: 0.87092 | O63: 0.87759 | P63: 0.88393 | Q63: 0.89002 | R63: 0.89596 | S63: 0.90188 | T63: 0.90789 | U63: 0.91418 | V63: 0.92093 | W63: 0.92834 | X63: 0.93652 | Y63: 0.9454 | Z63: 0.95468 | AA63: 0.96367 | AB63: 0.97087 | AC63: 1 | BF63: 0.75581 | BG63: 0.76794 | BH63: 0.77981 | BI63: 0.79146 | BJ63: 0.80287 | BK63: 0.814 | BL63: 0.82478 | BM63: 0.83514 | BN63: 0.84503 | BO63: 0.85442 | BP63: 0.86334 | BQ63: 0.87183 | BR63: 0.87996 | BS63: 0.8878 | BT63: 0.89546 | BU63: 0.90304 | BV63: 0.91069 | BW63: 0.91857 | BX63: 0.92687 | BY63: 0.93569 | BZ63: 0.945 | CA63: 0.95453 | CB63: 0.96363 | CC63: 0.97087 | CD63: 1
D64: 64 | E64: 0.80486 | F64: 0.81406 | G64: 0.82303 | H64: 0.83178 | I64: 0.84029 | J64: 0.84852 | K64: 0.8564 | L64: 0.86387 | M64: 0.87092 | N64: 0.87759 | O64: 0.88393 | P64: 0.89002 | Q64: 0.89596 | R64: 0.90188 | S64: 0.90789 | T64: 0.91418 | U64: 0.92093 | V64: 0.92834 | W64: 0.93652 | X64: 0.9454 | Y64: 0.95468 | Z64: 0.96367 | AA64: 0.97087 | AB64: 1 | BF64: 0.76794 | BG64: 0.77981 | BH64: 0.79146 | BI64: 0.80287 | BJ64: 0.814 | BK64: 0.82478 | BL64: 0.83514 | BM64: 0.84503 | BN64: 0.85442 | BO64: 0.86334 | BP64: 0.87183 | BQ64: 0.87996 | BR64: 0.8878 | BS64: 0.89546 | BT64: 0.90304 | BU64: 0.91069 | BV64: 0.91857 | BW64: 0.92687 | BX64: 0.93569 | BY64: 0.945 | BZ64: 0.95453 | CA64: 0.96363 | CB64: 0.97087 | CC64: 1
D65: 65 | E65: 0.81406 | F65: 0.82303 | G65: 0.83178 | H65: 0.84029 | I65: 0.84852 | J65: 0.8564 | K65: 0.86387 | L65: 0.87092 | M65: 0.87759 | N65: 0.88393 | O65: 0.89002 | P65: 0.89596 | Q65: 0.90188 | R65: 0.90789 | S65: 0.91418 | T65: 0.92093 | U65: 0.92834 | V65: 0.93652 | W65: 0.9454 | X65: 0.95468 | Y65: 0.96367 | Z65: 0.97087 | AA65: 1 | BF65: 0.77981 | BG65: 0.79146 | BH65: 0.80287 | BI65: 0.814 | BJ65: 0.82478 | BK65: 0.83514 | BL65: 0.84503 | BM65: 0.85442 | BN65: 0.86334 | BO65: 0.87183 | BP65: 0.87996 | BQ65: 0.8878 | BR65: 0.89546 | BS65: 0.90304 | BT65: 0.91069 | BU65: 0.91857 | BV65: 0.92687 | BW65: 0.93569 | BX65: 0.945 | BY65: 0.95453 | BZ65: 0.96363 | CA65: 0.97087 | CB65: 1
D66: 66 | E66: 0.82303 | F66: 0.83178 | G66: 0.84029 | H66: 0.84852 | I66: 0.8564 | J66: 0.86387 | K66: 0.87092 | L66: 0.87759 | M66: 0.88393 | N66: 0.89002 | O66: 0.89596 | P66: 0.90188 | Q66: 0.90789 | R66: 0.91418 | S66: 0.92093 | T66: 0.92834 | U66: 0.93652 | V66: 0.9454 | W66: 0.95468 | X66: 0.96367 | Y66: 0.97087 | Z66: 1 | BF66: 0.79146 | BG66: 0.80287 | BH66: 0.814 | BI66: 0.82478 | BJ66: 0.83514 | BK66: 0.84503 | BL66: 0.85442 | BM66: 0.86334 | BN66: 0.87183 | BO66: 0.87996 | BP66: 0.8878 | BQ66: 0.89546 | BR66: 0.90304 | BS66: 0.91069 | BT66: 0.91857 | BU66: 0.92687 | BV66: 0.93569 | BW66: 0.945 | BX66: 0.95453 | BY66: 0.96363 | BZ66: 0.97087 | CA66: 1
D67: 67 | E67: 0.83178 | F67: 0.84029 | G67: 0.84852 | H67: 0.8564 | I67: 0.86387 | J67: 0.87092 | K67: 0.87759 | L67: 0.88393 | M67: 0.89002 | N67: 0.89596 | O67: 0.90188 | P67: 0.90789 | Q67: 0.91418 | R67: 0.92093 | S67: 0.92834 | T67: 0.93652 | U67: 0.9454 | V67: 0.95468 | W67: 0.96367 | X67: 0.97087 | Y67: 1 | BF67: 0.80287 | BG67: 0.814 | BH67: 0.82478 | BI67: 0.83514 | BJ67: 0.84503 | BK67: 0.85442 | BL67: 0.86334 | BM67: 0.87183 | BN67: 0.87996 | BO67: 0.8878 | BP67: 0.89546 | BQ67: 0.90304 | BR67: 0.91069 | BS67: 0.91857 | BT67: 0.92687 | BU67: 0.93569 | BV67: 0.945 | BW67: 0.95453 | BX67: 0.96363 | BY67: 0.97087 | BZ67: 1
D68: 68 | E68: 0.84029 | F68: 0.84852 | G68: 0.8564 | H68: 0.86387 | I68: 0.87092 | J68: 0.87759 | K68: 0.88393 | L68: 0.89002 | M68: 0.89596 | N68: 0.90188 | O68: 0.90789 | P68: 0.91418 | Q68: 0.92093 | R68: 0.92834 | S68: 0.93652 | T68: 0.9454 | U68: 0.95468 | V68: 0.96367 | W68: 0.97087 | X68: 1 | BF68: 0.814 | BG68: 0.82478 | BH68: 0.83514 | BI68: 0.84503 | BJ68: 0.85442 | BK68: 0.86334 | BL68: 0.87183 | BM68: 0.87996 | BN68: 0.8878 | BO68: 0.89546 | BP68: 0.90304 | BQ68: 0.91069 | BR68: 0.91857 | BS68: 0.92687 | BT68: 0.93569 | BU68: 0.945 | BV68: 0.95453 | BW68: 0.96363 | BX68: 0.97087 | BY68: 1
D69: 69 | E69: 0.84852 | F69: 0.8564 | G69: 0.86387 | H69: 0.87092 | I69: 0.87759 | J69: 0.88393 | K69: 0.89002 | L69: 0.89596 | M69: 0.90188 | N69: 0.90789 | O69: 0.91418 | P69: 0.92093 | Q69: 0.92834 | R69: 0.93652 | S69: 0.9454 | T69: 0.95468 | U69: 0.96367 | V69: 0.97087 | W69: 1 | BF69: 0.82478 | BG69: 0.83514 | BH69: 0.84503 | BI69: 0.85442 | BJ69: 0.86334 | BK69: 0.87183 | BL69: 0.87996 | BM69: 0.8878 | BN69: 0.89546 | BO69: 0.90304 | BP69: 0.91069 | BQ69: 0.91857 | BR69: 0.92687 | BS69: 0.93569 | BT69: 0.945 | BU69: 0.95453 | BV69: 0.96363 | BW69: 0.97087 | BX69: 1
D70: 70 | E70: 0.8564 | F70: 0.86387 | G70: 0.87092 | H70: 0.87759 | I70: 0.88393 | J70: 0.89002 | K70: 0.89596 | L70: 0.90188 | M70: 0.90789 | N70: 0.91418 | O70: 0.92093 | P70: 0.92834 | Q70: 0.93652 | R70: 0.9454 | S70: 0.95468 | T70: 0.96367 | U70: 0.97087 | V70: 1 | BF70: 0.83514 | BG70: 0.84503 | BH70: 0.85442 | BI70: 0.86334 | BJ70: 0.87183 | BK70: 0.87996 | BL70: 0.8878 | BM70: 0.89546 | BN70: 0.90304 | BO70: 0.91069 | BP70: 0.91857 | BQ70: 0.92687 | BR70: 0.93569 | BS70: 0.945 | BT70: 0.95453 | BU70: 0.96363 | BV70: 0.97087 | BW70: 1
D71: 71 | E71: 0.86387 | F71: 0.87092 | G71: 0.87759 | H71: 0.88393 | I71: 0.89002 | J71: 0.89596 | K71: 0.90188 | L71: 0.90789 | M71: 0.91418 | N71: 0.92093 | O71: 0.92834 | P71: 0.93652 | Q71: 0.9454 | R71: 0.95468 | S71: 0.96367 | T71: 0.97087 | U71: 1 | BF71: 0.84503 | BG71: 0.85442 | BH71: 0.86334 | BI71: 0.87183 | BJ71: 0.87996 | BK71: 0.8878 | BL71: 0.89546 | BM71: 0.90304 | BN71: 0.91069 | BO71: 0.91857 | BP71: 0.92687 | BQ71: 0.93569 | BR71: 0.945 | BS71: 0.95453 | BT71: 0.96363 | BU71: 0.97087 | BV71: 1
D72: 72 | E72: 0.87092 | F72: 0.87759 | G72: 0.88393 | H72: 0.89002 | I72: 0.89596 | J72: 0.90188 | K72: 0.90789 | L72: 0.91418 | M72: 0.92093 | N72: 0.92834 | O72: 0.93652 | P72: 0.9454 | Q72: 0.95468 | R72: 0.96367 | S72: 0.97087 | T72: 1 | BF72: 0.85442 | BG72: 0.86334 | BH72: 0.87183 | BI72: 0.87996 | BJ72: 0.8878 | BK72: 0.89546 | BL72: 0.90304 | BM72: 0.91069 | BN72: 0.91857 | BO72: 0.92687 | BP72: 0.93569 | BQ72: 0.945 | BR72: 0.95453 | BS72: 0.96363 | BT72: 0.97087 | BU72: 1
D73: 73 | E73: 0.87759 | F73: 0.88393 | G73: 0.89002 | H73: 0.89596 | I73: 0.90188 | J73: 0.90789 | K73: 0.91418 | L73: 0.92093 | M73: 0.92834 | N73: 0.93652 | O73: 0.9454 | P73: 0.95468 | Q73: 0.96367 | R73: 0.97087 | S73: 1 | BF73: 0.86334 | BG73: 0.87183 | BH73: 0.87996 | BI73: 0.8878 | BJ73: 0.89546 | BK73: 0.90304 | BL73: 0.91069 | BM73: 0.91857 | BN73: 0.92687 | BO73: 0.93569 | BP73: 0.945 | BQ73: 0.95453 | BR73: 0.96363 | BS73: 0.97087 | BT73: 1
D74: 74 | E74: 0.88393 | F74: 0.89002 | G74: 0.89596 | H74: 0.90188 | I74: 0.90789 | J74: 0.91418 | K74: 0.92093 | L74: 0.92834 | M74: 0.93652 | N74: 0.9454 | O74: 0.95468 | P74: 0.96367 | Q74: 0.97087 | R74: 1 | BF74: 0.87183 | BG74: 0.87996 | BH74: 0.8878 | BI74: 0.89546 | BJ74: 0.90304 | BK74: 0.91069 | BL74: 0.91857 | BM74: 0.92687 | BN74: 0.93569 | BO74: 0.945 | BP74: 0.95453 | BQ74: 0.96363 | BR74: 0.97087 | BS74: 1
D75: 75 | E75: 0.89002 | F75: 0.89596 | G75: 0.90188 | H75: 0.90789 | I75: 0.91418 | J75: 0.92093 | K75: 0.92834 | L75: 0.93652 | M75: 0.9454 | N75: 0.95468 | O75: 0.96367 | P75: 0.97087 | Q75: 1 | BF75: 0.87996 | BG75: 0.8878 | BH75: 0.89546 | BI75: 0.90304 | BJ75: 0.91069 | BK75: 0.91857 | BL75: 0.92687 | BM75: 0.93569 | BN75: 0.945 | BO75: 0.95453 | BP75: 0.96363 | BQ75: 0.97087 | BR75: 1
D76: 76 | E76: 0.89596 | F76: 0.90188 | G76: 0.90789 | H76: 0.91418 | I76: 0.92093 | J76: 0.92834 | K76: 0.93652 | L76: 0.9454 | M76: 0.95468 | N76: 0.96367 | O76: 0.97087 | P76: 1 | BF76: 0.8878 | BG76: 0.89546 | BH76: 0.90304 | BI76: 0.91069 | BJ76: 0.91857 | BK76: 0.92687 | BL76: 0.93569 | BM76: 0.945 | BN76: 0.95453 | BO76: 0.96363 | BP76: 0.97087 | BQ76: 1
D77: 77 | E77: 0.90188 | F77: 0.90789 | G77: 0.91418 | H77: 0.92093 | I77: 0.92834 | J77: 0.93652 | K77: 0.9454 | L77: 0.95468 | M77: 0.96367 | N77: 0.97087 | O77: 1 | BF77: 0.89546 | BG77: 0.90304 | BH77: 0.91069 | BI77: 0.91857 | BJ77: 0.92687 | BK77: 0.93569 | BL77: 0.945 | BM77: 0.95453 | BN77: 0.96363 | BO77: 0.97087 | BP77: 1
D78: 78 | E78: 0.90789 | F78: 0.91418 | G78: 0.92093 | H78: 0.92834 | I78: 0.93652 | J78: 0.9454 | K78: 0.95468 | L78: 0.96367 | M78: 0.97087 | N78: 1 | BF78: 0.90304 | BG78: 0.91069 | BH78: 0.91857 | BI78: 0.92687 | BJ78: 0.93569 | BK78: 0.945 | BL78: 0.95453 | BM78: 0.96363 | BN78: 0.97087 | BO78: 1
D79: 79 | E79: 0.91418 | F79: 0.92093 | G79: 0.92834 | H79: 0.93652 | I79: 0.9454 | J79: 0.95468 | K79: 0.96367 | L79: 0.97087 | M79: 1 | BF79: 0.91069 | BG79: 0.91857 | BH79: 0.92687 | BI79: 0.93569 | BJ79: 0.945 | BK79: 0.95453 | BL79: 0.96363 | BM79: 0.97087 | BN79: 1
D80: 80 | E80: 0.92093 | F80: 0.92834 | G80: 0.93652 | H80: 0.9454 | I80: 0.95468 | J80: 0.96367 | K80: 0.97087 | L80: 1 | BF80: 0.91857 | BG80: 0.92687 | BH80: 0.93569 | BI80: 0.945 | BJ80: 0.95453 | BK80: 0.96363 | BL80: 0.97087 | BM80: 1
D81: 81 | E81: 0.92834 | F81: 0.93652 | G81: 0.9454 | H81: 0.95468 | I81: 0.96367 | J81: 0.97087 | K81: 1 | BF81: 0.92687 | BG81: 0.93569 | BH81: 0.945 | BI81: 0.95453 | BJ81: 0.96363 | BK81: 0.97087 | BL81: 1
D82: 82 | E82: 0.93652 | F82: 0.9454 | G82: 0.95468 | H82: 0.96367 | I82: 0.97087 | J82: 1 | BF82: 0.93569 | BG82: 0.945 | BH82: 0.95453 | BI82: 0.96363 | BJ82: 0.97087 | BK82: 1
D83: 83 | E83: 0.9454 | F83: 0.95468 | G83: 0.96367 | H83: 0.97087 | I83: 1 | BF83: 0.945 | BG83: 0.95453 | BH83: 0.96363 | BI83: 0.97087 | BJ83: 1
D84: 84 | E84: 0.95468 | F84: 0.96367 | G84: 0.97087 | H84: 1 | BF84: 0.95453 | BG84: 0.96363 | BH84: 0.97087 | BI84: 1
D85: 85 | E85: 0.96367 | F85: 0.97087 | G85: 1 | BF85: 0.96363 | BG85: 0.97087 | BH85: 1
D86: 86 | E86: 0.97087 | F86: 1 | BF86: 0.97087 | BG86: 1
D87: 87 | E87: 1 | BF87: 1
